Workbook

Sheet LEVEL PREMIUM Model
A1: Level Premium Insurance Female age 40 Smoker Spring 2024
A2: Input Items: (rows 1-21) | E2: Section | F2: 1 | G2: Input Items
A3: Number of Policies Sold Fall 2024 | B3: 100000
A4: Average Face amount Per Policy | B4: ='Sensitivity Tests'!B1 -> 300000
A5: Earned Interest Rate | B5: ='Sensitivity Tests'!B46 -> 0.043 | C5: =B5 -> 0.043 | D5: =C5 -> 0.043 | E5: =D5 -> 0.043 | F5: =E5 -> 0.043 | G5: =F5 -> 0.043 | H5: =G5 -> 0.043 | I5: =H5 -> 0.043 | J5: =I5 -> 0.043 | K5: =J5 -> 0.043
A7: Expenses
A8: Acquisition Expense Per Policy | B8: ='Sensitivity Tests'!B6 -> 50
A9: Acquisition Expense Per $1000 face amount | B9: ='Sensitivity Tests'!B11 -> 0.25
A10: Maintenance Expense Per Policy Per year | B10: ='Sensitivity Tests'!B16 -> 10
A11: Maintenance Expense Per $1000 inforce | B11: ='Sensitivity Tests'!B21 -> 0.05
A12: Tax rate | B12: ='Sensitivity Tests'!B26 -> 0.21
A13: Year | B13: 1 | C13: 2 | D13: 3 | E13: 4 | F13: 5 | G13: 6 | H13: 7 | I13: 8 | J13: 9 | K13: 10
A14: Premium per $1000 | B14: 2.4 | C14: 2.4 | D14: 2.4 | E14: 2.4 | F14: 2.4 | G14: 2.4 | H14: 2.4 | I14: 2.4 | J14: 2.4 | K14: 2.4
A15: First year Lapse rate | B15: ='Sensitivity Tests'!B38 -> 0.2
A16: Renewal Years Lapse rates | C16: ='Sensitivity Tests'!B42 -> 0.1 | D16: =C16 -> 0.1 | E16: =D16 -> 0.1 | F16: =E16 -> 0.1 | G16: =F16 -> 0.1 | H16: =G16 -> 0.1 | I16: =H16 -> 0.1 | J16: =I16 -> 0.1 | K16: 1
A17: First year Comission rate | B17: 0.7
A18: Renewal Commission rate | C18: 0.05 | D18: =$C$18 -> 0.05 | E18: =$C$18 -> 0.05 | F18: =$C$18 -> 0.05 | G18: =$C$18 -> 0.05 | H18: =$C$18 -> 0.05 | I18: =$C$18 -> 0.05 | J18: =$C$18 -> 0.05 | K18: =$C$18 -> 0.05
A19: Age | B19: 40 | C19: =B19+1 -> 41 | D19: =C19+1 -> 42 | E19: =D19+1 -> 43 | F19: =E19+1 -> 44 | G19: =F19+1 -> 45 | H19: =G19+1 -> 46 | I19: =H19+1 -> 47 | J19: =I19+1 -> 48 | K19: =J19+1 -> 49
A20: Best Estimate mortality rate | B20: =$B$100*B101 -> 0.00079722 | C20: =$B$100*C101 -> 0.00098262 | D20: =$B$100*D101 -> 0.0012051 | E20: =$B$100*E101 -> 0.00146466 | F20: =$B$100*F101 -> 0.00175203 | G20: =$B$100*G101 -> 0.00208575 | H20: =$B$100*H101 -> 0.00245655 | I20: =$B$100*I101 -> 0.00286443 | ... K20: =$B$100*K101 -> 0.0038007
A21: Benchmark Surplus as % of expected one year claims | B21: 0.25
A22: Notes and assumptions:
A23: Timing of cash Flows: | B23: Premiums and acquisition expenses (incl commissions) are paid at the beginning of the year
B24: Death benefits and maintenance expenses occur uniformly throughout the year
E25: Section | F25: 2 | G25: Intermediate Calculations
A26: Beginning of Year | B26: 1 | C26: 2 | D26: 3 | E26: 4 | F26: 5 | G26: 6 | H26: 7 | I26: 8 | J26: 9 | K26: 10 | L26: 11
A27: Number of policies in force | B27: =B3 -> 100000 | C27: =B27*(1-B20)*(1-B15) -> 79936.222 | D27: =C27*(1-C20)*(1-C16) -> 71871.908 | E27: =D27*(1-D16)*(1-D20) -> 64606.766 | F27: =E27*(1-E20)*(1-E16) -> 58060.925 | G27: =F27*(1-F20)*(1-F16) -> 52163.28 | H27: =G27*(1-G20)*(1-G16) -> 46849.033 | I27: =H27*(1-H20)*(1-H16) -> 42060.551 | J27: =I27*(1-I20)*(1-I16) -> 37746.064 | K27: =J27*(1-J20)*(1-J16) -> 33858.718
A28: Face Amount in Force | B28: =B27*B4 -> 30000000000 | C28: =C27*B4 -> 23980866720 | D28: =D27*B4 -> 2.1561572e+10 | E28: =E27*B4 -> 1.938203e+10 | F28: =F27*B4 -> 1.7418277e+10 | G28: =G27*B4 -> 1.5648984e+10 | H28: =H27*B4 -> 1.405471e+10 | I28: =I27*B4 -> 1.2618165e+10 | J28: =J27*B4 -> 1.1323819e+10 | K28: =K27*B4 -> 1.0157615e+10
A30: Statutory Income Statement- Cash Flows | E30: Section | F30: 2.967772 | G30: Statutory Income
A31: Year | B31: 1 | C31: 2 | D31: 3 | E31: 4 | F31: 5 | G31: 6 | H31: 7 | I31: 8 | J31: 9 | K31: 10 | L31: 11
A32: Premiums | B32: =B27*(B4/1000)*B14 -> 72000000 | C32: =C27*(B4/1000)*C14 -> 57554080 | D32: =D27*(B4/1000)*D14 -> 51747774 | E32: =E27*(B4/1000)*E14 -> 46516871 | F32: =F27*(B4/1000)*F14 -> 41803866 | G32: =G27*(B4/1000)*G14 -> 37557562 | H32: =H27*(B4/1000)*H14 -> 33731303 | I32: =I27*(B4/1000)*I14 -> 30283597 | J32: =J27*(B4/1000)*J14 -> 27177166 | K32: =K27*(B4/1000)*K14 -> 24378277
A33: Net Investment Income | B33: =(B32-B38-B40)*B5-(B36+B39)*(B5/2) -> -176656.9 | C33: =((B87+C32-C40)*B5)-((C36+C39)*(B5/2)) -> 2436384.2 | D33: =((C87+D32-D40)*C5)-((D36+D39)*(C5/2)) -> 3207864.9 | E33: =((D87+E32-E40)*D5)-((E36+E39)*(D5/2)) -> 3611255.8 | F33: =((E87+F32-F40)*E5)-((F36+F39)*(E5/2)) -> 3700063.8 | G33: =((F87+G32-G40)*F5)-((G36+G39)*(F5/2)) -> 3521917.1 | H33: =((G87+H32-H40)*G5)-((H36+H39)*(G5/2)) -> 3118037.9 | I33: =((H87+I32-I40)*H5)-((I36+I39)*(H5/2)) -> 2530834.2 | J33: =((I87+J32-J40)*I5)-((J36+J39)*(I5/2)) -> 1796995 | K33: =((J87+K32-K40)*J5)-((K36+K39)*(J5/2)) -> 952150.48
A34: Sub-total-income | B34: =B32+B33 -> 71823343 | C34: =C32+C33 -> 59990464 | D34: =D32+D33 -> 54955639 | E34: =E32+E33 -> 50128127 | F34: =F32+F33 -> 45503930 | G34: =G32+G33 -> 41079479 | H34: =H32+H33 -> 36849341 | I34: =I32+I33 -> 32814431 | ... K34: =K32+K33 -> 25330428
A36: Death Benefits Paid | B36: =B28*B20 -> 23916600 | C36: =C28*C20 -> 23564079 | D36: =D28*D20 -> 25983851 | E36: =E28*E20 -> 28388084 | F36: =F28*F20 -> 30517345 | G36: =G28*G20 -> 32639869 | H36: =H28*H20 -> 34526097 | I36: =I28*I20 -> 36143851 | ... K36: =K28*K20 -> 38606049
A37: Expenses:
A38: Acquisition | B38: =(B3*B8)+(B28/1000)*B9 -> 12500000
A39: Maintenance | B39: =(B3*B10)+(B76/1000)*B11 -> 2500000 | C39: =(C27*B10)+(C28/1000)*B11 -> 1998405.6 | D39: =(D27*B10)+(D28/1000)*B11 -> 1796797.7 | E39: =(E27*B10)+(E28/1000)*B11 -> 1615169.1 | F39: =(F27*B10)+(F28/1000)*B11 -> 1451523.1 | G39: =(G27*B10)+(G28/1000)*B11 -> 1304082 | H39: =(H27*B10)+(H28/1000)*B11 -> 1171225.8 | I39: =(I27*B10)+(I28/1000)*B11 -> 1051513.8 | J39: =(J27*B10)+(J28/1000)*B11 -> 943651.61 | K39: =(K27*B10)+(K28/1000)*B11 -> 846467.96
A40: Commissions | B40: =B32*B17 -> 50400000 | C40: =C32*C18 -> 2877704 | D40: =D32*D18 -> 2587388.7 | E40: =E32*E18 -> 2325843.6 | F40: =F32*F18 -> 2090193.3 | G40: =G32*G18 -> 1877878.1 | H40: =H32*H18 -> 1686565.2 | I40: =I32*I18 -> 1514179.8 | J40: =J32*J18 -> 1358858.3 | K40: =K32*K18 -> 1218913.9
A41: Change in Reserve | B41: =B88 -> 14764965 | C41: =C88 -> 24566483 | D41: =D88 -> 15461843 | E41: =E88 -> 7525465 | F41: =F88 -> 878585.21 | G41: =G88 -> -4880907.5 | H41: =H88 -> -9631558.4 | I41: =I88 -> -13450824 | ... K41: =K88 -> -18709930
A42: Sub-total-benefits and expenses | B42: =B36+B38+B39+B40+B41 -> 1.0408156e+08 | C42: =C36+C38+C39+C40+C41 -> 53006672 | D42: =D36+D39+D40+D41 -> 45829880 | E42: =E36+E39+E40+E41 -> 39854561 | F42: =F36+F39+F40+F41 -> 34937646 | G42: =G36+G39+G40+G41 -> 30940921 | H42: =H36+H39+H40+H41 -> 27752330 | I42: =I36+I39+I40+I41 -> 25258721 | J42: =J36+J39+J40+J41 -> 23358294 | K42: =K36+K39+K40+K41 -> 21961501 | L42: 0
A44: Pre-tax income | B44: =B32+B33-B42 -> -32258221 | C44: =C32+C33-C42 -> 6983792.1 | D44: =D32+D33-D42 -> 9125758.4 | E44: =E32+E33-E42 -> 10273566 | F44: =F32+F33-F42 -> 10566283 | G44: =G32+G33-G42 -> 10138558 | H44: =H32+H33-H42 -> 9097011.6 | I44: =I32+I33-I42 -> 7555709.7 | ... K44: =K32+K33-K42 -> 3368926.3 | L44: 0
A45: Taxes | B45: =B12*B44 -> -6774226.5 | C45: =B12*C44 -> 1466596.3 | D45: =B12*D44 -> 1916409.3 | E45: =B12*E44 -> 2157448.8 | F45: =B12*F44 -> 2218919.5 | G45: =B12*G44 -> 2129097.1 | H45: =B12*H44 -> 1910372.4 | I45: =B12*I44 -> 1586699 | J45: =B12*J44 -> 1179332.1 | K45: =B12*K44 -> 707474.53 | L45: 0
A46: After-tax Income | B46: =B44-B45 -> -25483995 | C46: =C44-C45 -> 5517195.8 | D46: =D44-D45 -> 7209349.2 | E46: =E44-E45 -> 8116116.9 | F46: =F44-F45 -> 8347363.9 | G46: =G44-G45 -> 8009460.7 | H46: =H44-H45 -> 7186639.1 | I46: =I44-I45 -> 5969010.7 | ... K46: =K44-K45 -> 2661451.8 | L46: 0
A48: Opportunity Cost of Capital | B48: 0.13
A49: Net Present Value of Cash Flows | B49: =NPV($B$48, B46:L46) -> 7681427.3
A50: IRR | B50: =IRR(B46:L46, $B$48) -> 0.22126017
A52: Effect of Benchmark Surplus: | B52: 1 | C52: 2 | D52: 3 | E52: 4 | F52: 5 | G52: 6 | H52: 7 | I52: 8 | J52: 9 | K52: 10 | L52: 11
A53: After-tax interest earned on Benchmark Surplus | B53: =B93 -> 203111.73 | C53: =C93 -> 200117.94 | D53: =D93 -> 220667.85 | E53: =E93 -> 241085.8 | F53: =F93 -> 259168.55 | G53: =G93 -> 277194.08 | H53: =H93 -> 293212.88 | I53: =I93 -> 306951.66 | ... K53: =K93 -> 327861.87 | L53: 0
A54: Increase in Benchmark Surplus | B54: =B92 -> 5979150 | C54: =C92 -> -88130.186 | D54: =D92 -> 604942.9 | E54: =E92 -> 601058.18 | F54: =F92 -> 532315.26 | G54: =G92 -> 530630.98 | H54: =H92 -> 471557.2 | I54: =I92 -> 404438.49 | ... L54: =L92 -> -9651512.3
A55: Total Distributable Earnings | B55: =B46-B54+B53 -> -31260033 | C55: =C46-C54+C53 -> 5805443.9 | D55: =D46-D54+D53 -> 6825074.1 | E55: =E46-E54+E53 -> 7756144.5 | F55: =F46-F54+F53 -> 8074217.2 | G55: =G46-G54+G53 -> 7756023.8 | H55: =H46-H54+H53 -> 7008294.8 | I55: =I46-I54+I53 -> 5871523.8 | ... L55: =L46-L54+L53 -> 9651512.3
A56: Risk Adjusted IRR | B56: =IRR(B55:L55,B48) -> 0.1699142
A57: Net present value of Distributable earnings | B57: =NPV(B48,B55,C55,D55,E55,F55,G55,H55,I55,J55,K55) -> 1933809.6
A59: Statutory Reserve Calculations: Fall 2024 | E59: Section Spring 2023 | F59: 4.22 | G59: Statutory Reserves
A60: Statutory Assumptions
A61: Interest rate | B61: 0.03
A62: Age: | B62: =B19 -> 40 | C62: =B62+1 -> 41 | D62: =C62+1 -> 42 | E62: =D62+1 -> 43 | F62: =E62+1 -> 44 | G62: =F62+1 -> 45 | H62: =G62+1 -> 46 | I62: =H62+1 -> 47 | J62: =I62+1 -> 48 | K62: =J62+1 -> 49
A63: STAT mortality assumption = 2001 CSO | B63: 0.00086 | C63: 0.00106 | D63: 0.0013 | E63: 0.00158 | F63: 0.00189 | G63: 0.00225 | H63: 0.00265 | I63: 0.00309 | J63: 0.00358 | K63: 0.0041
A65: Statutory Lapse rates
A66: Year | B66: 1 | C66: 2 | D66: 3 | E66: 4 | F66: 5 | G66: 6 | H66: 7 | I66: 8 | J66: 9 | K66: 10
A67: Lapse rates | C67: 0 | D67: 0 | E67: 0 | F67: 0 | G67: 0 | H67: 0 | I67: 0 | J67: 0 | K67: =K16 -> 1
B68: 0
A69: Beginning of Year Fall 2024 | B69: 1 | C69: 2 | D69: 3 | E69: 4 | F69: 5 | G69: 6 | H69: 7 | I69: 8 | J69: 9 | K69: 10 | L69: 11
A70: Number of policies in force | B70: =B27 -> 100000 | C70: =B70*(1-B63)*(1-B68) -> 99914 | D70: =C70*(1-C63)*(1-C67) -> 99808.091 | E70: =D70*(1-D63)*(1-D67) -> 99678.341 | F70: =E70*(1-E63)*(1-E67) -> 99520.849 | G70: =F70*(1-F63)*(1-F67) -> 99332.754 | H70: =G70*(1-G63)*(1-G67) -> 99109.256 | I70: =H70*(1-H63)*(1-H67) -> 98846.616 | J70: =I70*(1-I63)*(1-I67) -> 98541.18 | K70: =J70*(1-J63)*(1-J67) -> 98188.403 | L70: =K70*(1-K63)*(1-K67) -> 0
A71: Premium | B71: =B70*(B4/1000)*B14 -> 72000000 | C71: =C70*(B4/1000)*C14 -> 71938080 | D71: =D70*(B4/1000)*D14 -> 71861826 | E71: =E70*(B4/1000)*E14 -> 71768405 | F71: =F70*(B4/1000)*F14 -> 71655011 | G71: =G70*(B4/1000)*G14 -> 71519583 | H71: =H70*(B4/1000)*H14 -> 71358664 | I71: =I70*(B4/1000)*I14 -> 71169564 | J71: =J70*(B4/1000)*J14 -> 70949650 | K71: =K70*(B4/1000)*K14 -> 70695650 | L71: =L70*(B4/1000)*L14 -> 0
A72: Acq Exp | B72: =(B3*B8)+(B28/1000)*B9 -> 12500000
A73: Maintenance expenses | B73: =(B70*B10)+(B76/1000)*B11 -> 2500000 | C73: =(C70*B10)+(C76/1000)*B11 -> 2497850 | D73: =(D70*B10)+(D76/1000)*B11 -> 2495202.3 | E73: =(E70*B10)+(E76/1000)*B11 -> 2491958.5 | F73: =(F70*B10)+(F76/1000)*B11 -> 2488021.2 | G73: =(G70*B10)+(G76/1000)*B11 -> 2483318.9 | H73: =(H70*B10)+(H76/1000)*B11 -> 2477731.4 | I73: =(I70*B10)+(I76/1000)*B11 -> 2471165.4 | J73: =(J70*B10)+(J76/1000)*B11 -> 2463529.5 | K73: =(K70*B10)+(K76/1000)*B11 -> 2454710.1 | L73: =(L70*L10)+(L76/1000)*L11 -> 0
A74: Commissions | B74: =B71*B17 -> 50400000 | C74: =C71*C18 -> 3596904 | D74: =D71*D18 -> 3593091.3 | E74: =E71*E18 -> 3588420.3 | F74: =F71*F18 -> 3582750.6 | G74: =G71*G18 -> 3575979.2 | H74: =H71*H18 -> 3567933.2 | I74: =I71*I18 -> 3558478.2 | J74: =J71*J18 -> 3547482.5 | ... L74: =L71*L18 -> 0
A75: Death benefits | B75: =B76*B63 -> 25800000 | C75: =C76*C63 -> 31772652 | D75: =D76*D63 -> 38925156 | E75: =E76*E63 -> 47247533 | F75: =F76*F63 -> 56428321 | G75: =G76*G63 -> 67049609 | H75: =H76*H63 -> 78791858 | I75: =I76*I63 -> 91630813 | ... L75: =L76*L63 -> 0
A76: Face Amount In-Force | B76: =B70*B4 -> 30000000000 | C76: =C70*B4 -> 29974200000 | D76: =D70*B4 -> 2.9942427e+10 | E76: =E70*B4 -> 2.9903502e+10 | F76: =F70*B4 -> 2.9856255e+10 | G76: =G70*B4 -> 2.9799826e+10 | H76: =H70*B4 -> 2.9732777e+10 | I76: =I70*B4 -> 2.9653985e+10 | J76: =J70*B4 -> 2.9562354e+10 | K76: =K70*B4 -> 2.9456521e+10 | L76: =L70*B4 -> 0
A78: End of year | B78: 1 | C78: 2.24 | D78: 2.967772 | E78: 4 | F78: 5 | G78: 6 | H78: 7 | I78: 8 | J78: 9 | K78: =J78+1 -> 10
A79: STAT Reserve equals
A80: PV future benefits | B80: =NPV(B61,C75:K75)*(1+B61)^0.5 -> 5.4331879e+08 | C80: =NPV(B61,D75:L75)*(1+B61)^0.5 -> 5.2737263e+08 | D80: =NPV(B61,E75:M75)*(1+B61)^0.5 -> 5.0368909e+08 | E80: =NPV(B61,F75:N75)*(1+B61)^0.5 -> 4.7084876e+08 | F80: =NPV(B61,G75:O75)*(1+B61)^0.5 -> 4.2770573e+08 | G80: =NPV(B61,H75:P75)*(1+B61)^0.5 -> 3.7248898e+08 | H80: =NPV(B61,I75:Q75)*(1+B61)^0.5 -> 3.0369865e+08 | I80: =NPV(B61,J75:R75)*(1+B61)^0.5 -> 2.1981449e+08 | J80: =NPV(B61,K75:S75)*(1+B61)^0.5 -> 1.1899993e+08 | K80: =NPV(B61,L75:T75)*(1+B61)^0.5 -> 0
A81: plus PV future maint expenses | B81: =NPV(B61, C73:K73)*(1+B61)^(0.5) -> 19608344 | C81: =NPV(B61, D73:L73)*(1+B61)^(0.5) -> 17661553 | D81: =NPV(B61, E73:M73)*(1+B61)^(0.5) -> 15659046 | E81: =NPV(B61, F73:N73)*(1+B61)^(0.5) -> 13599756 | F81: =NPV(B61, G73:O73)*(1+B61)^(0.5) -> 11482683 | G81: =NPV(B61, H73:P73)*(1+B61)^(0.5) -> 9306869.9 | H81: =NPV(B61, I73:Q73)*(1+B61)^(0.5) -> 7071453.3 | I81: =NPV(B61, J73:R73)*(1+B61)^(0.5) -> 4775637.9 | J81: =NPV(B61, K73:S73)*(1+B61)^(0.5) -> 2418697.7 | K81: =NPV(K61, L73:T73)*(1+K61)^(0.5) -> 0
A82: plus PV future commissions | B82: =NPV(B61,C74:K74)*(1+B61) -> 28656426 | C82: =NPV(B61,D74:L74)*(1+B61) -> 25811307 | D82: =NPV(B61,E74:M74)*(1+B61) -> 22884763 | E82: =NPV(B61,F74:N74)*(1+B61) -> 19875233 | F82: =NPV(B61,G74:O74)*(1+B61) -> 16781256 | G82: =NPV(B61,H74:P74)*(1+B61) -> 13601436 | H82: =NPV(B61,I74:Q74)*(1+B61) -> 10334507 | I82: =NPV(B61,J74:R74)*(1+B61) -> 6979310.2 | J82: =NPV(B61,K74:S74)*(1+B61) -> 3534782.5 | K82: =NPV(B61,L74:T74)*(1+B61) -> 0
A83: minus PV future Premiums | B83: =NPV(B61,C71:K71)*(1+B61) -> 5.7312851e+08 | C83: =NPV(B61,D71:L71)*(1+B61) -> 5.1622615e+08 | D83: =NPV(B61,E71:M71)*(1+B61) -> 4.5769525e+08 | E83: =NPV(B61,F71:N71)*(1+B61) -> 3.9750465e+08 | F83: =NPV(B61,G71:O71)*(1+B61) -> 3.3562513e+08 | G83: =NPV(B61,H71:P71)*(1+B61) -> 2.7202871e+08 | H83: =NPV(B61,I71:Q71)*(1+B61) -> 2.0669015e+08 | I83: =NPV(B61,J71:R71)*(1+B61) -> 1.395862e+08 | J83: =NPV(B61,K71:S71)*(1+B61) -> 70695650 | K83: =NPV(B61,L71:T71)*(1+B61) -> 0
A84: STAT reserve | B84: =MAX(0,B80+B81+B82-B83) -> 18455046 | C84: =MAX(0,C80+C81+C82-C83) -> 54619348 | D84: =MAX(0,D80+D81+D82-D83) -> 84537653 | E84: =MAX(0,E80+E81+E82-E83) -> 1.068191e+08 | F84: =MAX(0,F80+F81+F82-F83) -> 1.2034454e+08 | G84: =MAX(0,G80+G81+G82-G83) -> 1.2336857e+08 | H84: =MAX(0,H80+H81+H82-H83) -> 1.1441446e+08 | I84: =MAX(0,I80+I81+I82-I83) -> 91983232 | ... K84: =MAX(0,K80+K81+K82-K83) -> 0
A85: In Force based on statutory reserve assumptions | B85: =C76 -> 29974200000 | C85: =D76 -> 2.9942427e+10 | D85: =E76 -> 2.9903502e+10 | E85: =F76 -> 2.9856255e+10 | F85: =G76 -> 2.9799826e+10 | G85: =H76 -> 2.9732777e+10 | H85: =I76 -> 2.9653985e+10 | I85: =J76 -> 2.9562354e+10 | ... K85: =L76 -> 0
A86: Best Estimate In Force insurance amount | B86: =C28 -> 23980866720 | C86: =D28 -> 2.1561572e+10 | D86: =E28 -> 1.938203e+10 | E86: =F28 -> 1.7418277e+10 | F86: =G28 -> 1.5648984e+10 | G86: =H28 -> 1.405471e+10 | H86: =I28 -> 1.2618165e+10 | I86: =J28 -> 1.1323819e+10 | ... K86: =L28
A87: Stat Reserve for Best Estimate In-Force Amount | B87: =(B86/B85)*B84 -> 14764965 | C87: =(C86/C85)*C84 -> 39331448 | D87: =(D86/D85)*D84 -> 54793291 | E87: =(E86/E85)*E84 -> 62318756 | F87: =(F86/F85)*F84 -> 63197341 | G87: =(G86/G85)*G84 -> 58316434 | H87: =(H86/H85)*H84 -> 48684875 | I87: =(I86/I85)*I84 -> 35234051 | J87: =(J86/J85)*J84 -> 18709930 | K87: 0
A88: Increase in STAT Reserve | B88: =B87 -> 14764965 | C88: =C87-B87 -> 24566483 | D88: =D87-C87 -> 15461843 | E88: =E87-D87 -> 7525465 | F88: =F87-E87 -> 878585.21 | G88: =G87-F87 -> -4880907.5 | H88: =H87-G87 -> -9631558.4 | I88: =I87-H87 -> -13450824 | J88: =J87-I87 -> -16524122 | K88: =K87-J87 -> -18709930
B89: =0 -> 0 | C89: =B89 -> 0
A90: Benchmark Surplus calculations: | B90: 1 | C90: =B90+1 -> 2 | D90: =C90+1 -> 3 | E90: =D90+1 -> 4 | F90: =E90+1 -> 5 | G90: =F90+1 -> 6 | H90: =G90+1 -> 7 | I90: =H90+1 -> 8 | J90: 9 | K90: =J90+1 -> 10 | L90: =K90+1 -> 11
A91: Benchmark Surplus | B91: =B21*B36 -> 5979150 | C91: =B21*C36 -> 5891019.8 | D91: =B21*D36 -> 6495962.7 | E91: =B21*E36 -> 7097020.9 | F91: =B21*F36 -> 7629336.2 | G91: =B21*G36 -> 8159967.1 | H91: =B21*H36 -> 8631524.3 | I91: =B21*I36 -> 9035962.8 | J91: =B21*J36 -> 9394976.6 | K91: =B21*K36 -> 9651512.3 | L91: 0
A92: Change in Benchmark Surplus | B92: =B91 -> 5979150 | C92: =C91-B91 -> -88130.186 | D92: =D91-C91 -> 604942.9 | E92: =E91-D91 -> 601058.18 | F92: =F91-E91 -> 532315.26 | G92: =G91-F91 -> 530630.98 | H92: =H91-G91 -> 471557.2 | I92: =I91-H91 -> 404438.49 | J92: =J91-I91 -> 359013.74 | ... L92: =L91-K91 -> -9651512.3
A93: After-tax Interest earned on Benchmark | B93: =B91*B5*(1-B12) -> 203111.73 | C93: =C91*C5*(1-B12) -> 200117.94 | D93: =D91*D5*(1-B12) -> 220667.85 | E93: =E91*E5*(1-B12) -> 241085.8 | F93: =F91*F5*(1-B12) -> 259168.55 | G93: =G91*G5*(1-B12) -> 277194.08 | H93: =H91*H5*(1-B12) -> 293212.88 | I93: =I91*I5*(1-B12) -> 306951.66 | J93: =J91*J5*(1-B12) -> 319147.35 | K93: =K91*K5*(1-B12) -> 327861.87 | L93: 0
A96: Fall 2021
A99: Year | B99: 1 | C99: 2 | D99: 3 | E99: 4 | F99: 5 | G99: 6 | H99: 7 | I99: 8 | J99: 9 | K99: 10
A100: Mortality Factor | B100: ='Sensitivity Tests'!B30 -> 1
A101: Best estimate mortality rates | B101: 0.00079722 | C101: 0.00098262 | D101: 0.0012051 | E101: 0.00146466 | F101: 0.00175203 | G101: 0.00208575 | H101: 0.00245655 | I101: 0.00286443 | J101: 0.00331866 | K101: 0.0038007

Sheet YRT Model
A1: Yearly Renewable Term Insurance Female age 40 Smoker Spring 2024
A2: Input Items: (rows 1-21) | E2: Section | F2: 1 | G2: Input Items
A3: Number of Policies Sold Fall 2024 | B3: 100000
A4: Average Face amount Per Policy | B4: ='Sensitivity Tests'!B1 -> 300000
A5: Earned Interest Rate | B5: ='Sensitivity Tests'!B46 -> 0.043 | C5: =B5 -> 0.043 | D5: =C5 -> 0.043 | E5: =D5 -> 0.043 | F5: =E5 -> 0.043 | G5: =F5 -> 0.043 | H5: =G5 -> 0.043 | I5: =H5 -> 0.043 | J5: =I5 -> 0.043 | K5: =J5 -> 0.043
A7: Expenses
A8: Acquisition Expense Per Policy | B8: ='Sensitivity Tests'!B6 -> 50
A9: Acquisition Expense Per $1000 face amount | B9: ='Sensitivity Tests'!B11 -> 0.25
A10: Maintenance Expense Per Policy Per year | B10: ='Sensitivity Tests'!B16 -> 10
A11: Maintenance Expense Per $1000 inforce | B11: ='Sensitivity Tests'!B21 -> 0.05
A12: Tax rate | B12: ='Sensitivity Tests'!B26 -> 0.21
A13: Year | B13: 1 | C13: 2 | D13: 3 | E13: 4 | F13: 5 | G13: 6 | H13: 7 | I13: 8 | J13: 9 | K13: 10
A14: Premium per $1000 | B14: 1.07 | C14: 1.33 | D14: 1.62 | E14: 1.95 | F14: 2.32 | G14: 2.76 | H14: 3.24 | I14: 3.76 | J14: 4.35 | K14: 4.97
A15: First year Lapse rate | B15: ='Sensitivity Tests'!B38 -> 0.2
A16: Renewal Years Lapse rates | C16: ='Sensitivity Tests'!B42 -> 0.1 | D16: =C16 -> 0.1 | E16: =D16 -> 0.1 | F16: =E16 -> 0.1 | G16: =F16 -> 0.1 | H16: =G16 -> 0.1 | I16: =H16 -> 0.1 | J16: =I16 -> 0.1 | K16: 1
A17: First year Comission rate | B17: 0.7
A18: Renewal Commission rate | C18: 0.05 | D18: =$C$18 -> 0.05 | E18: =$C$18 -> 0.05 | F18: =$C$18 -> 0.05 | G18: =$C$18 -> 0.05 | H18: =$C$18 -> 0.05 | I18: =$C$18 -> 0.05 | J18: =$C$18 -> 0.05 | K18: =$C$18 -> 0.05
A19: Age | B19: 40 | C19: =B19+1 -> 41 | D19: =C19+1 -> 42 | E19: =D19+1 -> 43 | F19: =E19+1 -> 44 | G19: =F19+1 -> 45 | H19: =G19+1 -> 46 | I19: =H19+1 -> 47 | J19: =I19+1 -> 48 | K19: =J19+1 -> 49
A20: Best Estimate mortality rate | B20: =$B$100*B101 -> 0.00079722 | C20: =$B$100*C101 -> 0.00098262 | D20: =$B$100*D101 -> 0.0012051 | E20: =$B$100*E101 -> 0.00146466 | F20: =$B$100*F101 -> 0.00175203 | G20: =$B$100*G101 -> 0.00208575 | H20: =$B$100*H101 -> 0.00245655 | I20: =$B$100*I101 -> 0.00286443 | ... K20: =$B$100*K101 -> 0.0038007
A21: Benchmark Surplus as % of expected one year claims | B21: 0.25
A22: Notes and assumptions:
A23: Timing of cash Flows: | B23: Premiums and acquisition expenses (incl commissions) are paid at the beginning of the year
B24: Death benefits and maintenance expenses occur uniformly throughout the year
E25: Section | F25: 2 | G25: Intermediate Calculations
A26: Beginning of Year | B26: 1 | C26: 2 | D26: 3 | E26: 4 | F26: 5 | G26: 6 | H26: 7 | I26: 8 | J26: 9 | K26: 10 | L26: 11
A27: Number of policies in force | B27: =B3 -> 100000 | C27: =B27*(1-B20)*(1-B15) -> 79936.222 | D27: =C27*(1-C20)*(1-C16) -> 71871.908 | E27: =D27*(1-D16)*(1-D20) -> 64606.766 | F27: =E27*(1-E20)*(1-E16) -> 58060.925 | G27: =F27*(1-F20)*(1-F16) -> 52163.28 | H27: =G27*(1-G20)*(1-G16) -> 46849.033 | I27: =H27*(1-H20)*(1-H16) -> 42060.551 | J27: =I27*(1-I20)*(1-I16) -> 37746.064 | K27: =J27*(1-J20)*(1-J16) -> 33858.718
A28: Face Amount in Force | B28: =B27*B4 -> 30000000000 | C28: =C27*B4 -> 23980866720 | D28: =D27*B4 -> 2.1561572e+10 | E28: =E27*B4 -> 1.938203e+10 | F28: =F27*B4 -> 1.7418277e+10 | G28: =G27*B4 -> 1.5648984e+10 | H28: =H27*B4 -> 1.405471e+10 | I28: =I27*B4 -> 1.2618165e+10 | J28: =J27*B4 -> 1.1323819e+10 | K28: =K27*B4 -> 1.0157615e+10
A30: Statutory Income Statement- Cash Flows | E30: Section | F30: 2.967772 | G30: Statutory Income
A31: Year | B31: 1 | C31: 2 | D31: 3 | E31: 4 | F31: 5 | G31: 6 | H31: 7 | I31: 8 | J31: 9 | K31: 10 | L31: 11
A32: Premiums | B32: =B27*(B4/1000)*B14 -> 32100000 | C32: =C27*(B4/1000)*C14 -> 31894553 | D32: =D27*(B4/1000)*D14 -> 34929747 | E32: =E27*(B4/1000)*E14 -> 37794958 | F32: =F27*(B4/1000)*F14 -> 40410404 | G32: =G27*(B4/1000)*G14 -> 43191196 | H32: =H27*(B4/1000)*H14 -> 45537260 | I32: =I27*(B4/1000)*I14 -> 47444302 | J32: =J27*(B4/1000)*J14 -> 49258614 | K32: =K27*(B4/1000)*K14 -> 50483349
A33: Net Investment Income | B33: =(B32-B38-B40)*B5-(B36+B39)*(B5/2) -> -691366.9 | C33: =((B87+C32-C40)*B5)-((C36+C39)*(B5/2)) -> 753299.06 | D33: =((C87+D32-D40)*C5)-((D36+D39)*(C5/2)) -> 829596.23 | E33: =((D87+E32-E40)*D5)-((E36+E39)*(D5/2)) -> 898854.1 | F33: =((E87+F32-F40)*E5)-((F36+F39)*(E5/2)) -> 963434.33 | G33: =((F87+G32-G40)*F5)-((G36+G39)*(F5/2)) -> 1034565.4 | H33: =((G87+H32-H40)*G5)-((H36+H39)*(G5/2)) -> 1092704.6 | I33: =((H87+I32-I40)*H5)-((I36+I39)*(H5/2)) -> 1138399.4 | J33: =((I87+J32-J40)*I5)-((J36+J39)*(I5/2)) -> 1183957.9 | K33: =((J87+K32-K40)*J5)-((K36+K39)*(J5/2)) -> 1214015.7
A34: Sub-total-income | B34: =B32+B33 -> 31408633 | C34: =C32+C33 -> 32647852 | D34: =D32+D33 -> 35759343 | E34: =E32+E33 -> 38693812 | F34: =F32+F33 -> 41373838 | G34: =G32+G33 -> 44225761 | H34: =H32+H33 -> 46629964 | I34: =I32+I33 -> 48582701 | ... K34: =K32+K33 -> 51697365
A36: Death Benefits Paid | B36: =B28*B20 -> 23916600 | C36: =C28*C20 -> 23564079 | D36: =D28*D20 -> 25983851 | E36: =E28*E20 -> 28388084 | F36: =F28*F20 -> 30517345 | G36: =G28*G20 -> 32639869 | H36: =H28*H20 -> 34526097 | I36: =I28*I20 -> 36143851 | ... K36: =K28*K20 -> 38606049
A37: Expenses:
A38: Acquisition | B38: =(B3*B8)+(B28/1000)*B9 -> 12500000
A39: Maintenance | B39: =(B3*B10)+(B76/1000)*B11 -> 2500000 | C39: =(C27*B10)+(C28/1000)*B11 -> 1998405.6 | D39: =(D27*B10)+(D28/1000)*B11 -> 1796797.7 | E39: =(E27*B10)+(E28/1000)*B11 -> 1615169.1 | F39: =(F27*B10)+(F28/1000)*B11 -> 1451523.1 | G39: =(G27*B10)+(G28/1000)*B11 -> 1304082 | H39: =(H27*B10)+(H28/1000)*B11 -> 1171225.8 | I39: =(I27*B10)+(I28/1000)*B11 -> 1051513.8 | J39: =(J27*B10)+(J28/1000)*B11 -> 943651.61 | K39: =(K27*B10)+(K28/1000)*B11 -> 846467.96
A40: Commissions | B40: =B32*B17 -> 22470000 | C40: =C32*C18 -> 1594727.6 | D40: =D32*D18 -> 1746487.4 | E40: =E32*E18 -> 1889747.9 | F40: =F32*F18 -> 2020520.2 | G40: =G32*G18 -> 2159559.8 | H40: =H32*H18 -> 2276863 | I40: =I32*I18 -> 2372215.1 | J40: =J32*J18 -> 2462930.7 | K40: =K32*K18 -> 2524167.4
A41: Change in Reserve | B41: =B88 -> 0 | C41: =C88 -> 0 | D41: =D88 -> 0 | E41: =E88 -> 0 | F41: =F88 -> 0 | G41: =G88 -> 0 | H41: =H88 -> 0 | I41: =I88 -> 0 | ... K41: =K88 -> 0
A42: Sub-total-benefits and expenses | B42: =B36+B38+B39+B40+B41 -> 61386600 | C42: =C36+C38+C39+C40+C41 -> 27157212 | D42: =D36+D39+D40+D41 -> 29527136 | E42: =E36+E39+E40+E41 -> 31893001 | F42: =F36+F39+F40+F41 -> 33989388 | G42: =G36+G39+G40+G41 -> 36103510 | H42: =H36+H39+H40+H41 -> 37974186 | I42: =I36+I39+I40+I41 -> 39567580 | J42: =J36+J39+J40+J41 -> 40986489 | K42: =K36+K39+K40+K41 -> 41976685 | L42: 0
A44: Pre-tax income | B44: =B32+B33-B42 -> -29977967 | C44: =C32+C33-C42 -> 5490639.3 | D44: =D32+D33-D42 -> 6232207.5 | E44: =E32+E33-E42 -> 6800811.3 | F44: =F32+F33-F42 -> 7384450.1 | G44: =G32+G33-G42 -> 8122251.1 | H44: =H32+H33-H42 -> 8655778.2 | I44: =I32+I33-I42 -> 9015120.8 | ... K44: =K32+K33-K42 -> 9720680.1 | L44: 0
A45: Taxes | B45: =B12*B44 -> -6295373 | C45: =B12*C44 -> 1153034.3 | D45: =B12*D44 -> 1308763.6 | E45: =B12*E44 -> 1428170.4 | F45: =B12*F44 -> 1550734.5 | G45: =B12*G44 -> 1705672.7 | H45: =B12*H44 -> 1817713.4 | I45: =B12*I44 -> 1893175.4 | J45: =B12*J44 -> 1985777.5 | K45: =B12*K44 -> 2041342.8 | L45: 0
A46: After-tax Income | B46: =B44-B45 -> -23682594 | C46: =C44-C45 -> 4337605.1 | D46: =D44-D45 -> 4923444 | E46: =E44-E45 -> 5372641 | F46: =F44-F45 -> 5833715.6 | G46: =G44-G45 -> 6416578.4 | H46: =H44-H45 -> 6838064.8 | I46: =I44-I45 -> 7121945.5 | ... K46: =K44-K45 -> 7679337.2 | L46: 0
A48: Opportunity Cost of Capital | B48: 0.13
A49: Net Present Value of Cash Flows | B49: =NPV($B$48, B46:L46) -> 5729153.9
A50: IRR | B50: =IRR(B46:L46, $B$48) -> 0.19234671
A52: Effect of Benchmark Surplus: | B52: 1 | C52: 2 | D52: 3 | E52: 4 | F52: 5 | G52: 6 | H52: 7 | I52: 8 | J52: 9 | K52: 10 | L52: 11
A53: After-tax interest earned on Benchmark Surplus | B53: =B93 -> 203111.73 | C53: =C93 -> 200117.94 | D53: =D93 -> 220667.85 | E53: =E93 -> 241085.8 | F53: =F93 -> 259168.55 | G53: =G93 -> 277194.08 | H53: =H93 -> 293212.88 | I53: =I93 -> 306951.66 | ... K53: =K93 -> 327861.87 | L53: 0
A54: Increase in Benchmark Surplus | B54: =B92 -> 5979150 | C54: =C92 -> -88130.186 | D54: =D92 -> 604942.9 | E54: =E92 -> 601058.18 | F54: =F92 -> 532315.26 | G54: =G92 -> 530630.98 | H54: =H92 -> 471557.2 | I54: =I92 -> 404438.49 | ... L54: =L92 -> -9651512.3
A55: Total Distributable Earnings | B55: =B46-B54+B53 -> -29458632 | C55: =C46-C54+C53 -> 4625853.2 | D55: =D46-D54+D53 -> 4539168.9 | E55: =E46-E54+E53 -> 5012668.6 | F55: =F46-F54+F53 -> 5560568.8 | G55: =G46-G54+G53 -> 6163141.5 | H55: =H46-H54+H53 -> 6659720.5 | I55: =I46-I54+I53 -> 7024458.6 | ... L55: =L46-L54+L53 -> 9651512.3
A56: Risk Adjusted IRR | B56: =IRR(B55:L55,B48) -> 0.15057227
A57: Net present value of Distributable earnings | B57: =NPV(B48,B55,C55,D55,E55,F55,G55,H55,I55,J55,K55,L55) -> 2497662.7
A59: Statutory Reserve Calculations: Fall 2024 | E59: Section Spring 2023 | F59: 4.22 | G59: Statutory Reserves
A60: Statutory Assumptions
A61: Interest rate | B61: 0.03
A62: Age: | B62: =B19 -> 40 | C62: =B62+1 -> 41 | D62: =C62+1 -> 42 | E62: =D62+1 -> 43 | F62: =E62+1 -> 44 | G62: =F62+1 -> 45 | H62: =G62+1 -> 46 | I62: =H62+1 -> 47 | J62: =I62+1 -> 48 | K62: =J62+1 -> 49
A63: STAT mortality assumption = 2001 CSO | B63: 0.00086 | C63: 0.00106 | D63: 0.0013 | E63: 0.00158 | F63: 0.00189 | G63: 0.00225 | H63: 0.00265 | I63: 0.00309 | J63: 0.00358 | K63: 0.0041
A65: Statutory Lapse rates
A66: Year | B66: 1 | C66: 2 | D66: 3 | E66: 4 | F66: 5 | G66: 6 | H66: 7 | I66: 8 | J66: 9 | K66: 10
A67: Lapse rates | B67: 0 | C67: 0 | D67: 0 | E67: 0 | F67: 0 | G67: 0 | H67: 0 | I67: 0 | J67: 0 | K67: =K16 -> 1
A69: Beginning of Year Fall 2024 | B69: 1 | C69: 2 | D69: 3 | E69: 4 | F69: 5 | G69: 6 | H69: 7 | I69: 8 | J69: 9 | K69: 10 | L69: 11
A70: Number of policies in force | B70: =B27 -> 100000 | C70: =B70*(1-B63)*(1-B67) -> 99914 | D70: =C70*(1-C63)*(1-C67) -> 99808.091 | E70: =D70*(1-D63)*(1-D67) -> 99678.341 | F70: =E70*(1-E63)*(1-E67) -> 99520.849 | G70: =F70*(1-F63)*(1-F67) -> 99332.754 | H70: =G70*(1-G63)*(1-G67) -> 99109.256 | I70: =H70*(1-H63)*(1-H67) -> 98846.616 | J70: =I70*(1-I63)*(1-I67) -> 98541.18 | ... L70: =K70*(1-K63)*(1-K67) -> 0
A71: Premium | B71: =B70*(B4/1000)*B14 -> 32100000 | C71: =C70*(B4/1000)*C14 -> 39865686 | D71: =D70*(B4/1000)*D14 -> 48506732 | E71: =E70*(B4/1000)*E14 -> 58311829 | F71: =F70*(B4/1000)*F14 -> 69266511 | G71: =G70*(B4/1000)*G14 -> 82247521 | H71: =H70*(B4/1000)*H14 -> 96334197 | I71: =I70*(B4/1000)*I14 -> 1.1149898e+08 | J71: =J70*(B4/1000)*J14 -> 1.2859624e+08 | K71: =K70*(B4/1000)*K14 -> 1.4639891e+08 | L71: =L70*(B4/1000)*L14 -> 0
A72: Acq Exp | B72: =(B3*B8)+(B28/1000)*B9 -> 12500000
A73: Maintenance expenses | B73: =(B70*B10)+(B76/1000)*B11 -> 2500000 | C73: =(C70*B10)+(C76/1000)*B11 -> 2497850 | D73: =(D70*B10)+(D76/1000)*B11 -> 2495202.3 | E73: =(E70*B10)+(E76/1000)*B11 -> 2491958.5 | F73: =(F70*B10)+(F76/1000)*B11 -> 2488021.2 | G73: =(G70*B10)+(G76/1000)*B11 -> 2483318.9 | H73: =(H70*B10)+(H76/1000)*B11 -> 2477731.4 | I73: =(I70*B10)+(I76/1000)*B11 -> 2471165.4 | J73: =(J70*B10)+(J76/1000)*B11 -> 2463529.5 | K73: =(K70*B10)+(K76/1000)*B11 -> 2454710.1 | L73: =(L70*L10)+(L76/1000)*L11 -> 0
A74: Commissions | B74: =B71*B17 -> 22470000 | C74: =C71*C18 -> 1993284.3 | D74: =D71*D18 -> 2425336.6 | E74: =E71*E18 -> 2915591.5 | F74: =F71*F18 -> 3463325.5 | G74: =G71*G18 -> 4112376 | H74: =H71*H18 -> 4816709.8 | I74: =I71*I18 -> 5574949.2 | J74: =J71*J18 -> 6429812 | ... L74: =L71*L18 -> 0
A75: Death benefits | B75: =B76*B63 -> 25800000 | C75: =C76*C63 -> 31772652 | D75: =D76*D63 -> 38925156 | E75: =E76*E63 -> 47247533 | F75: =F76*F63 -> 56428321 | G75: =G76*G63 -> 67049609 | H75: =H76*H63 -> 78791858 | I75: =I76*I63 -> 91630813 | ... L75: =L76*L63 -> 0
A76: Face Amount In-Force | B76: =B70*B4 -> 30000000000 | C76: =C70*B4 -> 29974200000 | D76: =D70*B4 -> 2.9942427e+10 | E76: =E70*B4 -> 2.9903502e+10 | F76: =F70*B4 -> 2.9856255e+10 | G76: =G70*B4 -> 2.9799826e+10 | H76: =H70*B4 -> 2.9732777e+10 | I76: =I70*B4 -> 2.9653985e+10 | J76: =J70*B4 -> 2.9562354e+10 | K76: =K70*B4 -> 2.9456521e+10 | L76: =L70*B4 -> 0
A78: End of year | B78: 1 | C78: 2.24 | D78: 2.967772 | E78: 4 | F78: 5 | G78: 6 | H78: 7 | I78: 8 | J78: 9 | K78: =J78+1 -> 10
A79: STAT Reserve equals
A80: PV future benefits | B80: =NPV(B61,C75:K75)*(1+B61)^0.5 -> 5.4331879e+08 | C80: =NPV(B61,D75:L75)*(1+B61)^0.5 -> 5.2737263e+08 | D80: =NPV(B61,E75:M75)*(1+B61)^0.5 -> 5.0368909e+08 | E80: =NPV(B61,F75:N75)*(1+B61)^0.5 -> 4.7084876e+08 | F80: =NPV(B61,G75:O75)*(1+B61)^0.5 -> 4.2770573e+08 | G80: =NPV(B61,H75:P75)*(1+B61)^0.5 -> 3.7248898e+08 | H80: =NPV(B61,I75:Q75)*(1+B61)^0.5 -> 3.0369865e+08 | I80: =NPV(B61,J75:R75)*(1+B61)^0.5 -> 2.1981449e+08 | J80: =NPV(B61,K75:S75)*(1+B61)^0.5 -> 1.1899993e+08 | K80: =NPV(B61,L75:T75)*(1+B61)^0.5 -> 0
A81: plus PV future maint expenses | B81: =NPV(B61, C73:K73)*(1+B61)^(0.5) -> 19608344 | C81: =NPV(B61, D73:L73)*(1+B61)^(0.5) -> 17661553 | D81: =NPV(B61, E73:M73)*(1+B61)^(0.5) -> 15659046 | E81: =NPV(B61, F73:N73)*(1+B61)^(0.5) -> 13599756 | F81: =NPV(B61, G73:O73)*(1+B61)^(0.5) -> 11482683 | G81: =NPV(B61, H73:P73)*(1+B61)^(0.5) -> 9306869.9 | H81: =NPV(B61, I73:Q73)*(1+B61)^(0.5) -> 7071453.3 | I81: =NPV(B61, J73:R73)*(1+B61)^(0.5) -> 4775637.9 | J81: =NPV(B61, K73:S73)*(1+B61)^(0.5) -> 2418697.7 | K81: =NPV(K61, L73:T73)*(1+K61)^(0.5) -> 0
A82: plus PV future commissions | B82: =NPV(B61,C74:K74)*(1+B61) -> 33749757 | C82: =NPV(B61,D74:L74)*(1+B61) -> 32709167 | D82: =NPV(B61,E74:M74)*(1+B61) -> 31192346 | E82: =NPV(B61,F74:N74)*(1+B61) -> 29125057 | F82: =NPV(B61,G74:O74)*(1+B61) -> 26431583 | G82: =NPV(B61,H74:P74)*(1+B61) -> 22988783 | H82: =NPV(B61,I74:Q74)*(1+B61) -> 18717236 | I82: =NPV(B61,J74:R74)*(1+B61) -> 13536555 | J82: =NPV(B61,K74:S74)*(1+B61) -> 7319945.4 | K82: =NPV(B61,L74:T74)*(1+B61) -> 0
A83: minus PV future Premiums | B83: =NPV(B61,C71:K71)*(1+B61) -> 6.7499515e+08 | C83: =NPV(B61,D71:L71)*(1+B61) -> 6.5418335e+08 | D83: =NPV(B61,E71:M71)*(1+B61) -> 6.2384691e+08 | E83: =NPV(B61,F71:N71)*(1+B61) -> 5.8250113e+08 | F83: =NPV(B61,G71:O71)*(1+B61) -> 5.2863166e+08 | G83: =NPV(B61,H71:P71)*(1+B61) -> 4.5977567e+08 | H83: =NPV(B61,I71:Q71)*(1+B61) -> 3.7434471e+08 | I83: =NPV(B61,J71:R71)*(1+B61) -> 2.707311e+08 | J83: =NPV(B61,K71:S71)*(1+B61) -> 1.4639891e+08 | K83: =NPV(B61,L71:T71)*(1+B61) -> 0
A84: STAT reserve | B84: =MAX(0,B80+B81+B82-B83) -> 0 | C84: =MAX(0,C80+C81+C82-C83) -> 0 | D84: =MAX(0,D80+D81+D82-D83) -> 0 | E84: =MAX(0,E80+E81+E82-E83) -> 0 | F84: =MAX(0,F80+F81+F82-F83) -> 0 | G84: =MAX(0,G80+G81+G82-G83) -> 0 | H84: =MAX(0,H80+H81+H82-H83) -> 0 | I84: =MAX(0,I80+I81+I82-I83) -> 0 | ... K84: =MAX(0,K80+K81+K82-K83) -> 0
A85: In Force based on statutory reserve assumptions | B85: =C76 -> 29974200000 | C85: =D76 -> 2.9942427e+10 | D85: =E76 -> 2.9903502e+10 | E85: =F76 -> 2.9856255e+10 | F85: =G76 -> 2.9799826e+10 | G85: =H76 -> 2.9732777e+10 | H85: =I76 -> 2.9653985e+10 | I85: =J76 -> 2.9562354e+10 | ... K85: =L76 -> 0
A86: Best Estimate In Force insurance amount | B86: =C28 -> 23980866720 | C86: =D28 -> 2.1561572e+10 | D86: =E28 -> 1.938203e+10 | E86: =F28 -> 1.7418277e+10 | F86: =G28 -> 1.5648984e+10 | G86: =H28 -> 1.405471e+10 | H86: =I28 -> 1.2618165e+10 | I86: =J28 -> 1.1323819e+10 | ... K86: =L28
A87: Stat Reserve for Best Estimate In-Force Amount | B87: =(B86/B85)*B84 -> 0 | C87: =(C86/C85)*C84 -> 0 | D87: =(D86/D85)*D84 -> 0 | E87: =(E86/E85)*E84 -> 0 | F87: =(F86/F85)*F84 -> 0 | G87: =(G86/G85)*G84 -> 0 | H87: =(H86/H85)*H84 -> 0 | I87: =(I86/I85)*I84 -> 0 | J87: =(J86/J85)*J84 -> 0 | K87: 0
A88: Increase in STAT Reserve | B88: =B87 -> 0 | C88: =C87-B87 -> 0 | D88: =D87-C87 -> 0 | E88: =E87-D87 -> 0 | F88: =F87-E87 -> 0 | G88: =G87-F87 -> 0 | H88: =H87-G87 -> 0 | I88: =I87-H87 -> 0 | J88: =J87-I87 -> 0 | K88: =K87-J87 -> 0
A90: Benchmark Surplus calculations: | B90: 1 | C90: =B90+1 -> 2 | D90: =C90+1 -> 3 | E90: =D90+1 -> 4 | F90: =E90+1 -> 5 | G90: =F90+1 -> 6 | H90: =G90+1 -> 7 | I90: =H90+1 -> 8 | J90: 9 | K90: =J90+1 -> 10 | L90: =K90+1 -> 11
A91: Benchmark Surplus | B91: =B21*B36 -> 5979150 | C91: =B21*C36 -> 5891019.8 | D91: =B21*D36 -> 6495962.7 | E91: =B21*E36 -> 7097020.9 | F91: =B21*F36 -> 7629336.2 | G91: =B21*G36 -> 8159967.1 | H91: =B21*H36 -> 8631524.3 | I91: =B21*I36 -> 9035962.8 | J91: =B21*J36 -> 9394976.6 | K91: =B21*K36 -> 9651512.3 | L91: 0
A92: Change in Benchmark Surplus | B92: =B91 -> 5979150 | C92: =C91-B91 -> -88130.186 | D92: =D91-C91 -> 604942.9 | E92: =E91-D91 -> 601058.18 | F92: =F91-E91 -> 532315.26 | G92: =G91-F91 -> 530630.98 | H92: =H91-G91 -> 471557.2 | I92: =I91-H91 -> 404438.49 | J92: =J91-I91 -> 359013.74 | ... L92: =L91-K91 -> -9651512.3
A93: After-tax Interest earned on Benchmark | B93: =B91*B5*(1-B12) -> 203111.73 | C93: =C91*C5*(1-B12) -> 200117.94 | D93: =D91*D5*(1-B12) -> 220667.85 | E93: =E91*E5*(1-B12) -> 241085.8 | F93: =F91*F5*(1-B12) -> 259168.55 | G93: =G91*G5*(1-B12) -> 277194.08 | H93: =H91*H5*(1-B12) -> 293212.88 | I93: =I91*I5*(1-B12) -> 306951.66 | J93: =J91*J5*(1-B12) -> 319147.35 | K93: =K91*K5*(1-B12) -> 327861.87
A96: Fall 2021
A99: Year | B99: 1 | C99: 2 | D99: 3 | E99: 4 | F99: 5 | G99: 6 | H99: 7 | I99: 8 | J99: 9 | K99: 10
A100: Mortality Factor | B100: ='Sensitivity Tests'!B30 -> 1
A101: Best estimate mortality rates | B101: 0.00079722 | C101: 0.00098262 | D101: 0.0012051 | E101: 0.00146466 | F101: 0.00175203 | G101: 0.00208575 | H101: 0.00245655 | I101: 0.00286443 | J101: 0.00331866 | K101: 0.0038007

Sheet Sensitivity Tests
A1: Average Face Amount Per Policy | B1: 300000 | C1: 100000 | D1: =C1+20000 -> 120000 | E1: =D1+20000 -> 140000 | F1: =E1+20000 -> 160000 | G1: =F1+20000 -> 180000 | H1: =G1+20000 -> 200000 | I1: =H1+20000 -> 220000 | J1: =I1+20000 -> 240000 | K1: =J1+20000 -> 260000 | ... U1: =T1+20000 -> 460000
A2: Level Premium | B2: ='LEVEL PREMIUM Model'!B56 -> 0.1699142 | C2: 0.06435708 | D2: 0.08411908 | E2: 0.1003098 | F2: 0.113859 | G2: 0.12538752 | H2: 0.13532962 | I2: 0.14400002 | J2: 0.1516334 | K2: 0.15840885 | L2: 0.1644657 | M2: 0.1699142 | N2: 0.1748428 | O2: 0.17932341 | P2: 0.18341508 | Q2: 0.18716682 | R2: 0.19061968 | S2: 0.19380828 | T2: 0.19676206 | U2: 0.1995062
A3: YRT | B3: ='YRT Model'!B56 -> 0.15057227 | C3: 0.06058427 | D3: 0.079637301 | E3: 0.094438523 | F3: 0.10629178 | G3: 0.11600968 | H3: 0.12412783 | I3: 0.13101478 | J3: 0.136933 | K3: 0.1420748 | L3: 0.14658442 | M3: 0.15057227 | N3: 0.15412434 | O3: 0.15730865 | P3: 0.16017968 | Q3: 0.16278166 | R3: 0.1651508 | S3: 0.16731711 | T3: 0.16930562 | U3: 0.17113741
A6: Acquisition Expense Per Policy | B6: 50 | C6: 45 | D6: =C6+1 -> 46 | E6: =D6+1 -> 47 | F6: =E6+1 -> 48 | G6: =F6+1 -> 49 | H6: =G6+1 -> 50 | I6: =H6+1 -> 51 | J6: =I6+1 -> 52 | K6: =J6+1 -> 53 | ... M6: =L6+1 -> 55
A7: Level Premium | B7: ='LEVEL PREMIUM Model'!B56 -> 0.1699142 | C7: 0.17364445 | D7: 0.17289194 | E7: 0.17214269 | F7: 0.17139666 | G7: 0.17065384 | H7: 0.1699142 | I7: 0.16917771 | J7: 0.16844437 | K7: 0.16771413 | L7: 0.16698699 | M7: 0.16626291
A8: YRT | B8: ='YRT Model'!B56 -> 0.15057227 | C8: 0.15382724 | D8: 0.15317062 | E8: 0.15251683 | F8: 0.15186585 | G8: 0.15121767 | H8: 0.15057227 | I8: 0.14992961 | J8: 0.14928969 | K8: 0.14865248 | L8: 0.14801796 | M8: 0.14738611
A11: Acquisition Expense Per $1000 face amount | B11: 0.25 | C11: 0.1 | D11: =C11+0.05 -> 0.15 | E11: =D11+0.05 -> 0.2 | F11: =E11+0.05 -> 0.25 | G11: =F11+0.05 -> 0.3 | H11: =G11+0.05 -> 0.35 | I11: =H11+0.05 -> 0.4 | J11: =I11+0.05 -> 0.45 | K11: =J11+0.05 -> 0.5 | ... M11: =L11+0.05 -> 0.6
A12: Level Premium | B12: =B7 -> 0.1699142 | C12: 0.2067179 | D12: 0.19358889 | E12: 0.18135378 | F12: 0.1699142 | G12: 0.15918617 | H12: 0.14909757 | I12: 0.13958605 | J12: 0.13059743 | K12: 0.12208435 | L12: 0.11400524 | M12: 0.10632344
A13: YRT | B13: =B8 -> 0.15057227 | C13: 0.18269696 | D13: 0.17123274 | E13: 0.16055443 | F13: 0.15057227 | G13: 0.14121032 | H13: 0.13240385 | I13: 0.12409728 | J13: 0.11624262 | K13: 0.10879813 | L13: 0.10172734 | M13: 0.094998234
A16: Maintenance Expense Per Policy Per year | B16: 10 | C16: 5 | D16: =C16+1 -> 6 | E16: =D16+1 -> 7 | F16: =E16+1 -> 8 | G16: =F16+1 -> 9 | H16: =G16+1 -> 10 | I16: =H16+1 -> 11 | J16: =I16+1 -> 12 | K16: =J16+1 -> 13 | ... M16: =L16+1 -> 15
A17: Level Premium | B17: =B12 -> 0.1699142 | C17: 0.19184619 | D17: 0.18719142 | E17: 0.18267772 | F17: 0.17829796 | G17: 0.17404552 | H17: 0.1699142 | I17: 0.16589824 | J17: 0.16199225 | K17: 0.1581912 | L17: 0.15449036 | M17: 0.1508853
A18: YRT | B18: =B13 -> 0.15057227 | C18: 0.16281258 | D18: 0.16033838 | E18: 0.15787738 | F18: 0.15542945 | G18: 0.15299445 | H18: 0.15057227 | I18: 0.14816277 | J18: 0.14576583 | K18: 0.14338133 | L18: 0.14100916 | M18: 0.13864918
A21: Maintenance Expense Per $1000 inforce | B21: 0.05 | C21: 0.01 | D21: =C21+0.01 -> 0.02 | E21: =D21+0.01 -> 0.03 | F21: =E21+0.01 -> 0.04 | G21: =F21+0.01 -> 0.05 | H21: =G21+0.01 -> 0.06 | I21: =H21+0.01 -> 0.07 | J21: =I21+0.01 -> 0.08 | K21: =J21+0.01 -> 0.09 | ... M21: =L21+0.01 -> 0.11
A22: Level Premium | B22: =B12 -> 0.1699142 | C22: 0.2291075 | D22: 0.21203868 | E22: 0.19664969 | F22: 0.18267772 | G22: 0.1699142 | H22: 0.1581912 | I22: 0.14737186 | J22: 0.13734333 | K22: 0.12801162 | L22: 0.11929776 | M22: 0.11113482
A23: YRT | B23: =B18 -> 0.15057227 | C23: 0.18051273 | D23: 0.172844 | E23: 0.16530011 | F23: 0.15787738 | G23: 0.15057227 | H23: 0.14338133 | I23: 0.13630127 | J23: 0.12932889 | K23: 0.12246108 | L23: 0.11569487 | M23: 0.10902737
A26: Tax Rate | B26: =21% -> 0.21 | C26: =0.15 -> 0.15 | D26: =C26+0.01 -> 0.16 | E26: =D26+0.01 -> 0.17 | F26: =E26+0.01 -> 0.18 | G26: =F26+0.01 -> 0.19 | H26: =G26+0.01 -> 0.2 | I26: =H26+0.01 -> 0.21 | J26: =I26+0.01 -> 0.22 | K26: =J26+0.01 -> 0.23 | ... M26: =L26+0.01 -> 0.25
A27: Level Premium | B27: =B22 -> 0.1699142 | C27: 0.17359489 | D27: 0.17300953 | E27: 0.17241334 | F27: 0.17180603 | G27: 0.17118728 | H27: 0.17055678 | I27: 0.1699142 | J27: 0.16925918 | K27: 0.16859139 | L27: 0.16791044 | M27: 0.16721595
A28: YRT | B28: =B23 -> 0.15057227 | C28: 0.15365557 | D28: 0.15316511 | E28: 0.15266562 | F28: 0.15215685 | G28: 0.15163855 | H28: 0.15111045 | I28: 0.15057227 | J28: 0.15002372 | K28: 0.14946451 | L28: 0.14889432 | M28: 0.14831284
A30: Mortality Factor | B30: 1 | C30: 0.7 | D30: =C30+0.01 -> 0.71 | E30: =D30+0.01 -> 0.72 | F30: =E30+0.01 -> 0.73 | G30: =F30+0.01 -> 0.74 | H30: =G30+0.01 -> 0.75 | I30: =H30+0.01 -> 0.76 | J30: =I30+0.01 -> 0.77 | K30: =J30+0.01 -> 0.78 | ... BH30: =BG30+0.01 -> 1.27
A31: Level Premium | B31: ='LEVEL PREMIUM Model'!B56 -> 0.1699142 | C31: 0.55124488 | D31: 0.53652779 | E31: 0.52202733 | F31: 0.5077339 | G31: 0.49363818 | H31: 0.47973113 | I31: 0.46600391 | J31: 0.4524479 | K31: 0.43905471 | L31: 0.42581609 | M31: 0.41272398 | N31: 0.39977044 | O31: 0.38694767 | P31: 0.37424798 | Q31: 0.36166377 | R31: 0.34918752 | S31: 0.33681177 | T31: 0.3245291 | U31: 0.3123321 | V31: 0.30021341 | W31: 0.2881656 | X31: 0.27618127 | Y31: 0.26425293 | Z31: 0.25237304 | AA31: 0.24053399 | AB31: 0.22872803 | AC31: 0.21694732 | AD31: 0.20518385 | AE31: 0.19342944 | AF31: 0.18167575 | AG31: 0.1699142 | AH31: 0.158136 | AI31: 0.14633211 | AJ31: 0.13449323 | AK31: 0.12260979 | AL31: 0.11067195 | AM31: 0.098669587 | AN31: 0.086592304 | AO31: 0.074429484 | AP31: 0.062170314 | AQ31: 0.049803865 | AR31: 0.037319193 | AS31: 0.024705491 | AT31: 0.011952292 | AU31: -0.0009502575 | AV31: -0.014011037 | AW31: -0.027237494 | AX31: -0.040635063 | AY31: -0.05420646 | AZ31: -0.067950847 | BA31: -0.081862875 | BB31: -0.095931663 | BC31: -0.11013978 | BD31: -0.12446234 | BE31: -0.13886641 | BF31: -0.15331087 | BG31: -0.16774693 | BH31: -0.18211946
A32: YRT | B32: ='YRT Model'!B56 -> 0.15057227 | C32: 0.52692967 | D32: 0.51177318 | E32: 0.49688148 | F32: 0.4822433 | G32: 0.46784783 | H32: 0.45368463 | I32: 0.43974365 | J32: 0.4260152 | K32: 0.41248992 | L32: 0.39915877 | M32: 0.38601301 | N32: 0.37304417 | O32: 0.36024406 | P32: 0.34760471 | Q32: 0.33511841 | R32: 0.32277766 | S32: 0.31057516 | T32: 0.29850381 | U32: 0.28655669 | V32: 0.27472705 | W32: 0.26300831 | X32: 0.25139404 | Y32: 0.23987795 | Z32: 0.22845389 | AA32: 0.21711584 | AB32: 0.20585791 | AC32: 0.19467434 | AD32: 0.18355946 | AE32: 0.17250775 | AF32: 0.16151378 | AG32: 0.15057227 | AH32: 0.13967801 | AI32: 0.12882598 | AJ32: 0.11801123 | AK32: 0.107229 | AL32: 0.096474667 | AM32: 0.085743775 | AN32: 0.075032065 | AO32: 0.064335492 | AP32: 0.053650251 | AQ32: 0.04297281 | AR32: 0.032299948 | AS32: 0.021628795 | AT32: 0.01095688 | AU32: 0.00028218423 | AV32: -0.010396801 | AW32: -0.021081012 | AX32: -0.031770748 | AY32: -0.042465602 | AZ32: -0.053164386 | BA32: -0.06386507 | BB32: -0.074564714 | BC32: -0.085259409 | BD32: -0.095944235 | BE32: -0.10661323 | BF32: -0.11725938 | BG32: -0.12787464 | BH32: -0.13844997
A34: Mortality Factor | B34: =1 -> 1
A35: Level Premium | B35: ='LEVEL PREMIUM Model'!B56 -> 0.1699142
A36: YRT | B36: ='YRT Model'!B56 -> 0.15057227
A38: First Year Lapse Rate | B38: =20% -> 0.2 | C38: 0.15 | D38: =C38+0.01 -> 0.16 | E38: =D38+0.01 -> 0.17 | F38: =E38+0.01 -> 0.18 | G38: =F38+0.01 -> 0.19 | H38: =G38+0.01 -> 0.2 | I38: =H38+0.01 -> 0.21 | J38: =I38+0.01 -> 0.22 | K38: =J38+0.01 -> 0.23 | ... P38: =O38+0.01 -> 0.28
A39: Level Premium | B39: ='LEVEL PREMIUM Model'!B56 -> 0.1699142 | C39: 0.17773827 | D39: 0.17621767 | E39: 0.17467548 | F39: 0.17311118 | G39: 0.17152427 | H39: 0.1699142 | I39: 0.16828041 | J39: 0.16662234 | K39: 0.1649394 | L39: 0.16323095 | M39: 0.16149638 | N39: 0.159735 | O39: 0.15794615 | P39: 0.15612911
A40: YRT | B40: ='YRT Model'!B56 -> 0.15057227 | C40: 0.16218467 | D40: 0.15989947 | E40: 0.15759603 | F40: 0.15527395 | G40: 0.15293284 | H40: 0.15057227 | I40: 0.14819181 | J40: 0.14579103 | K40: 0.14336946 | L40: 0.14092662 | M40: 0.13846202 | N40: 0.13597513 | O40: 0.13346544 | P40: 0.13093238
A42: Renewal Lapse Rates | B42: =10% -> 0.1 | C42: 0.05 | D42: =C42+0.01 -> 0.06 | E42: =D42+0.01 -> 0.07 | F42: =E42+0.01 -> 0.08 | G42: =F42+0.01 -> 0.09 | H42: =G42+0.01 -> 0.1 | I42: =H42+0.01 -> 0.11 | J42: =I42+0.01 -> 0.12 | K42: =J42+0.01 -> 0.13 | ... P42: =O42+0.01 -> 0.18
A43: Level Premium | B43: ='LEVEL PREMIUM Model'!B56 -> 0.1699142 | C43: 0.1189249 | D43: 0.12974711 | E43: 0.14027012 | F43: 0.15047843 | G43: 0.16036176 | H43: 0.1699142 | I43: 0.17913356 | J43: 0.18802065 | K43: 0.19657865 | L43: 0.20481262 | M43: 0.21272899 | N43: 0.22033526 | O43: 0.22763961 | P43: 0.23465073
A44: YRT | B44: ='YRT Model'!B56 -> 0.15057227 | C44: 0.18800541 | D44: 0.18053765 | E44: 0.17306033 | F44: 0.16557356 | G44: 0.15807749 | H44: 0.15057227 | I44: 0.14305803 | J44: 0.13553497 | K44: 0.12800324 | L44: 0.12046305 | M44: 0.1129146 | N44: 0.1053581 | O44: 0.097793795 | P44: 0.090221925
A46: Earned Interest Rate | B46: =4.3% -> 0.043 | C46: =0.02 -> 0.02 | D46: =C46+0.001 -> 0.021 | E46: =D46+0.001 -> 0.022 | F46: =E46+0.001 -> 0.023 | G46: =F46+0.001 -> 0.024 | H46: =G46+0.001 -> 0.025 | I46: =H46+0.001 -> 0.026 | J46: =I46+0.001 -> 0.027 | K46: =J46+0.001 -> 0.028 | ... AD46: =AC46+0.001 -> 0.047
A47: Level Premium | B47: ='LEVEL PREMIUM Model'!B56 -> 0.1699142 | C47: 0.113671 | D47: 0.11616022 | E47: 0.11864543 | F47: 0.12112663 | G47: 0.12360382 | H47: 0.12607699 | I47: 0.12854615 | J47: 0.13101131 | K47: 0.13347246 | L47: 0.13592961 | M47: 0.13838277 | N47: 0.14083194 | O47: 0.14327713 | P47: 0.14571835 | Q47: 0.1481556 | R47: 0.1505889 | S47: 0.15301826 | T47: 0.15544368 | U47: 0.15786517 | V47: 0.16028275 | W47: 0.16269643 | X47: 0.16510622 | Y47: 0.16751214 | Z47: 0.1699142 | AA47: 0.1723124 | AB47: 0.17470678 | AC47: 0.17709733 | AD47: 0.17948409
A48: YRT | B48: ='YRT Model'!B56 -> 0.15057227 | C48: 0.13151609 | D48: 0.13235815 | E48: 0.13319895 | F48: 0.13403849 | G48: 0.13487677 | H48: 0.13571381 | I48: 0.1365496 | J48: 0.13738416 | K48: 0.13821748 | L48: 0.13904957 | M48: 0.13988044 | N48: 0.14071009 | O48: 0.14153852 | P48: 0.14236574 | Q48: 0.14319175 | R48: 0.14401656 | S48: 0.14484017 | T48: 0.14566258 | U48: 0.14648381 | V48: 0.14730386 | W48: 0.14812272 | X48: 0.1489404 | Y48: 0.14975692 | Z48: 0.15057227 | AA48: 0.15138645 | AB48: 0.15219947 | AC48: 0.15301134 | AD48: 0.15382206
A51: Level Premium Scenario | D51: Mortality Factors
A52: Earned Interest Rate | B52: ='LEVEL PREMIUM Model'!B56 -> 0.1699142 | C52: 0.8 | D52: =C52+0.02 -> 0.82 | E52: =D52+0.02 -> 0.84 | F52: =E52+0.02 -> 0.86 | G52: =F52+0.02 -> 0.88 | H52: =G52+0.02 -> 0.9 | I52: =H52+0.02 -> 0.92 | J52: =I52+0.02 -> 0.94 | K52: =J52+0.02 -> 0.96 | ... W52: =V52+0.02 -> 1.2
B53: =3% -> 0.03 | C53: 0.38077442 | D53: 0.35526746 | E53: 0.33020602 | F53: 0.30552885 | G53: 0.28117529 | H53: 0.2570847 | I53: 0.23319589 | J53: 0.20944656 | K53: 0.18577265 | L53: 0.16210778 | M53: 0.13838277 | N53: 0.11452516 | O53: 0.090459124 | P53: 0.066105784 | Q53: 0.04138444 | R53: 0.016215254 | S53: -0.0094756543 | T53: -0.035747431 | U53: -0.062630559 | V53: -0.09010678 | W53: -0.11808399
B54: =B53+0.002 -> 0.032 | C54: 0.38570785 | D54: 0.36016134 | E54: 0.33506768 | F54: 0.31036575 | G54: 0.28599506 | H54: 0.26189523 | I54: 0.23800536 | J54: 0.21426347 | K54: 0.1906059 | L54: 0.16696672 | M54: 0.14327713 | N54: 0.11946507 | O54: 0.09545493 | P54: 0.071167767 | Q54: 0.046522281 | R54: 0.02143712 | S54: -0.0041645904 | T54: -0.030347258 | U54: -0.057149848 | V54: -0.084566665 | W54: -0.11252235
B55: =B54+0.002 -> 0.034 | C55: 0.39063459 | D55: 0.36504783 | E55: 0.33992121 | F55: 0.31519374 | G55: 0.2908051 | H55: 0.26669513 | I55: 0.24280323 | J55: 0.21906777 | K55: 0.1954255 | L55: 0.17181089 | M55: 0.1481556 | N55: 0.12438799 | O55: 0.10043271 | P55: 0.076210889 | Q55: 0.051640776 | R55: 0.026639763 | S55: 0.0011283571 | T55: -0.024962587 | U55: -0.051679851 | V55: -0.079029597 | W55: -0.10695271
B56: =B55+0.002 -> 0.036 | C56: 0.39555471 | D56: 0.36992701 | E56: 0.34476671 | F56: 0.3200129 | G56: 0.29560547 | H56: 0.27148448 | I56: 0.24758961 | J56: 0.22385958 | K56: 0.20023153 | L56: 0.17664038 | M56: 0.15301826 | N56: 0.12929394 | O56: 0.10539246 | P56: 0.081235054 | Q56: 0.056739702 | R56: 0.031822768 | S56: 0.0064024946 | T56: -0.019594499 | U56: -0.046222158 | V56: -0.073497762 | W56: -0.10137787
B57: =B56+0.002 -> 0.038 | C57: 0.40046828 | D57: 0.37479896 | E57: 0.34960424 | F57: 0.32482334 | G57: 0.30039629 | H57: 0.27626339 | I57: 0.2523646 | J57: 0.22863899 | K57: 0.20502409 | L57: 0.18145529 | M57: 0.15786517 | N57: 0.13418299 | O57: 0.11033418 | P57: 0.086240193 | Q57: 0.061818872 | R57: 0.036985773 | S57: 0.011657201 | T57: -0.014243983 | U57: -0.040778247 | V57: -0.067973235 | W57: -0.095800503
B58: =B57+0.002 -> 0.04 | C58: 0.40537536 | D58: 0.37966375 | E58: 0.35443389 | F58: 0.32962512 | G58: 0.30517763 | H58: 0.28103194 | I58: 0.2571283 | J58: 0.23340611 | K58: 0.2098033 | L58: 0.18625571 | M58: 0.16269643 | N58: 0.1390552 | O58: 0.11525789 | P58: 0.091226264 | Q58: 0.06687814 | R58: 0.042128467 | S58: 0.016891924 | T58: -0.0089119374 | U58: -0.035349487 | V58: -0.062457976 | W58: -0.09022322
B59: =B58+0.002 -> 0.042 | C59: 0.41027603 | D59: 0.38452145 | E59: 0.35925574 | F59: 0.33441834 | G59: 0.3099496 | H59: 0.28579026 | I59: 0.26188082 | J59: 0.23816105 | K59: 0.21456927 | L59: 0.19104177 | M59: 0.16751214 | N59: 0.14391064 | O59: 0.12016364 | P59: 0.09619325 | Q59: 0.071917391 | R59: 0.047250589 | S59: 0.022106176 | T59: -0.0035991758 | U59: -0.029937144 | V59: -0.056953826 | W59: -0.084648513
B60: =B59+0.002 -> 0.044 | C60: 0.41517035 | D60: 0.38937214 | E60: 0.36406988 | F60: 0.33920309 | G60: 0.3147123 | H60: 0.29053842 | I60: 0.26662227 | J60: 0.24290392 | K60: 0.2193221 | L60: 0.19581356 | M60: 0.1723124 | N60: 0.14874941 | O60: 0.12505148 | P60: 0.10114116 | Q60: 0.076936544 | R60: 0.05235192 | S60: 0.027299534 | T60: 0.0016935724 | U60: -0.024542375 | V60: -0.051462508 | W60: -0.079078764
B61: =B60+0.002 -> 0.046 | C61: 0.4200584 | D61: 0.3942159 | E61: 0.36887638 | F61: 0.34397946 | G61: 0.31946581 | H61: 0.29527655 | I61: 0.27135276 | J61: 0.24763484 | K61: 0.22406192 | L61: 0.20057122 | M61: 0.17709733 | N61: 0.15357161 | O61: 0.1299215 | P61: 0.10607001 | Q61: 0.081935547 | R61: 0.057432285 | S61: 0.03247163 | T61: 0.0069656562 | U61: -0.019166238 | V61: -0.045985625 | W61: -0.073516233
B62: =B61+0.002 -> 0.048 | C62: 0.42494024 | D62: 0.3990528 | E62: 0.37367533 | F62: 0.34874754 | G62: 0.32421023 | H62: 0.30000473 | I62: 0.27607239 | J62: 0.25235392 | K62: 0.22878885 | L62: 0.20531485 | M62: 0.18186705 | N62: 0.15837735 | O62: 0.13477377 | P62: 0.11097985 | Q62: 0.086914376 | R62: 0.062491547 | S62: 0.037622152 | T62: 0.0122165 | U62: -0.013809693 | V62: -0.040524659 | W62: -0.067963059
B63: =B62+0.002 -> 0.05 | C63: 0.42981595 | D63: 0.40388293 | E63: 0.37846682 | F63: 0.35350742 | G63: 0.32894566 | H63: 0.30472309 | I63: 0.28078127 | J63: 0.25706128 | K63: 0.23350301 | L63: 0.2100446 | M63: 0.18662168 | N63: 0.16316674 | O63: 0.13960839 | P63: 0.11587074 | Q63: 0.091873032 | R63: 0.067529607 | S63: 0.042750842 | T63: 0.017445598 | U63: -0.0084736032 | V63: -0.035080976 | W63: -0.062421249
B64: =B63+0.002 -> 0.052 | C64: 0.4346856 | D64: 0.40870634 | E64: 0.38325092 | F64: 0.35825918 | G64: 0.33367221 | H64: 0.30943171 | I64: 0.28547953 | J64: 0.26175704 | K64: 0.23820453 | L64: 0.21476058 | M64: 0.19136135 | N64: 0.1679399 | O64: 0.14442547 | P64: 0.12074277 | Q64: 0.096811538 | R64: 0.072546396 | S64: 0.047857486 | T64: 0.022652514 | U64: -0.0031587432 | V64: -0.029655827 | W64: -0.056892683
B65: =B64+0.002 -> 0.054 | C65: 0.43954925 | D65: 0.41352314 | E65: 0.38802772 | F65: 0.36300293 | G65: 0.33838996 | H65: 0.31413071 | I65: 0.29016728 | J65: 0.26644133 | K65: 0.24289354 | L65: 0.21946293 | M65: 0.19608619 | N65: 0.17269698 | O65: 0.14922513 | P65: 0.12559602 | Q65: 0.10172994 | R65: 0.077541881 | S65: 0.052941918 | T65: 0.027836874 | U65: 0.0021342 | V65: -0.024250352 | W65: -0.051379105
... B68: =B67+0.002 -> 0.06 | C68: 0.45410493 | D68: 0.42793451 | E68: 0.40231514 | F68: 0.37718694 | G68: 0.35249144 | H68: 0.32817106 | I68: 0.30416858 | J68: 0.28042656 | K68: 0.25688678 | L68: 0.23348958 | M68: 0.2101732 | N68: 0.18687306 | O68: 0.16352094 | P68: 0.14004425 | Q68: 0.11636527 | R68: 0.092400566 | S68: 0.068060867 | T68: 0.043251734 | U68: 0.017875861 | V68: -0.0081617525 | W68: -0.034943818
A71: YRT Scenario | D71: Mortality Factors
A72: Earned Interest Rate | B72: ='YRT Model'!B56 -> 0.15057227 | C72: 0.8 | D72: =C72+0.02 -> 0.82 | E72: =D72+0.02 -> 0.84 | F72: =E72+0.02 -> 0.86 | G72: =F72+0.02 -> 0.88 | H72: =G72+0.02 -> 0.9 | I72: =H72+0.02 -> 0.92 | J72: =I72+0.02 -> 0.94 | K72: =J72+0.02 -> 0.96 | ... W72: =V72+0.02 -> 1.2
B73: =0.03 -> 0.03 | C73: 0.37551058 | D73: 0.34978672 | E73: 0.32469257 | F73: 0.30016701 | G73: 0.27615222 | H73: 0.25259325 | I73: 0.22943774 | J73: 0.20663563 | K73: 0.184139 | L73: 0.16190193 | M73: 0.13988044 | N73: 0.11803262 | O73: 0.09631877 | P73: 0.074701844 | Q73: 0.053147998 | R73: 0.031627462 | S73: 0.010115687 | T73: -0.011405158 | U73: -0.032944353 | V73: -0.054500507 | W73: -0.076059301
B74: =B73+0.002 -> 0.032 | C74: 0.37713512 | D74: 0.3514046 | E74: 0.32630592 | F74: 0.30177799 | G74: 0.27776302 | H74: 0.2542061 | I74: 0.23105491 | J74: 0.20825945 | K74: 0.18577183 | L74: 0.16354617 | M74: 0.14153852 | N74: 0.11970694 | O74: 0.098011715 | P74: 0.076415693 | Q74: 0.054884865 | R74: 0.033389188 | S74: 0.011903706 | T74: -0.0095899884 | U74: -0.031101964 | V74: -0.052631854 | W74: -0.074166619
B75: =B74+0.002 -> 0.034 | C75: 0.37875644 | D75: 0.35301916 | E75: 0.32791583 | F75: 0.3033854 | G75: 0.2793701 | H75: 0.25581507 | I75: 0.23266804 | J75: 0.20987905 | K75: 0.18740025 | L75: 0.16518579 | M75: 0.14319175 | N75: 0.12137619 | O75: 0.099699348 | P75: 0.078123996 | Q75: 0.056615958 | R75: 0.035144932 | S75: 0.013685573 | T75: -0.0077810901 | U75: -0.029265886 | V75: -0.05076945 | W75: -0.072279991
B76: =B75+0.002 -> 0.036 | C76: 0.38037456 | D76: 0.35463042 | E76: 0.32952232 | F76: 0.30498926 | G76: 0.2809735 | H76: 0.25742021 | I76: 0.23427717 | J76: 0.21149446 | K76: 0.18902428 | L76: 0.16682082 | M76: 0.14484017 | N76: 0.12304039 | O76: 0.10138171 | P76: 0.079826791 | Q76: 0.058341317 | R76: 0.036894735 | S76: 0.015461322 | T76: -0.0059784322 | U76: -0.027436098 | V76: -0.048913283 | W76: -0.070399417
B77: =B76+0.002 -> 0.038 | C77: 0.38198949 | D77: 0.35623839 | E77: 0.33112542 | F77: 0.3065896 | G77: 0.28257323 | H77: 0.25902153 | I77: 0.23588232 | J77: 0.21310571 | K77: 0.19064397 | L77: 0.16845129 | M77: 0.14648381 | N77: 0.1246996 | O77: 0.10305884 | P77: 0.081524118 | Q77: 0.060060982 | R77: 0.038638635 | S77: 0.01723099 | T77: -0.0041819832 | U77: -0.025612575 | V77: -0.047063338 | W77: -0.068524897
B78: =B77+0.002 -> 0.04 | C78: 0.38360126 | D78: 0.35784309 | E78: 0.33272513 | F78: 0.30818643 | G78: 0.28416932 | H78: 0.26061907 | I78: 0.23748351 | J78: 0.21471284 | K78: 0.19225933 | L78: 0.17007724 | M78: 0.14812272 | N78: 0.12635384 | O78: 0.10473077 | P78: 0.083216018 | Q78: 0.061774992 | R78: 0.04037667 | S78: 0.018994614 | T78: -0.0023917114 | U78: -0.023795292 | V78: -0.045219602 | W78: -0.06665643
B79: =B78+0.002 -> 0.042 | C79: 0.38520988 | D79: 0.35944454 | E79: 0.33432149 | F79: 0.30977978 | G79: 0.2857618 | H79: 0.26221283 | I79: 0.23908078 | J79: 0.21631586 | K79: 0.1938704 | L79: 0.1716987 | M79: 0.14975692 | N79: 0.12800316 | O79: 0.10639754 | P79: 0.084902528 | Q79: 0.063483388 | R79: 0.042108879 | S79: 0.020752229 | T79: -0.00060758477 | U79: -0.021984224 | V79: -0.043382057 | W79: -0.064794012
B80: =B79+0.002 -> 0.044 | C80: 0.38681536 | D80: 0.36104277 | E80: 0.33591451 | F80: 0.31136968 | G80: 0.28735068 | H80: 0.26380286 | I80: 0.24067415 | J80: 0.21791481 | K80: 0.19547721 | L80: 0.17331569 | M80: 0.15138645 | N80: 0.12964758 | O80: 0.10805919 | P80: 0.086583688 | Q80: 0.065186207 | R80: 0.0438353 | S80: 0.022503872 | T80: 0.0011704291 | U80: -0.020179344 | V80: -0.041550688 | W80: -0.062937639
B81: =B80+0.002 -> 0.046 | C81: 0.38841774 | D81: 0.36263778 | E81: 0.33750421 | F81: 0.31295613 | G81: 0.288936 | H81: 0.26538918 | I81: 0.24226365 | J81: 0.21950971 | K81: 0.1970798 | L81: 0.17492826 | M81: 0.15301134 | N81: 0.13128714 | O81: 0.10971576 | P81: 0.088259536 | Q81: 0.066883489 | R81: 0.045555972 | S81: 0.02424958 | T81: 0.0029423628 | U81: -0.018380627 | V81: -0.039725477 | W81: -0.061087307
B82: =B81+0.002 -> 0.048 | C82: 0.39001701 | D82: 0.36422961 | E82: 0.33909061 | F82: 0.31453917 | G82: 0.29051777 | H82: 0.2669718 | I82: 0.2438493 | J82: 0.2211006 | K82: 0.19867818 | L82: 0.17653644 | M82: 0.15463163 | N82: 0.13292189 | O82: 0.11136729 | P82: 0.089930111 | Q82: 0.068575273 | R82: 0.047270933 | S82: 0.025989388 | T82: 0.0047082491 | U82: -0.016588046 | V82: -0.037906405 | W82: -0.059243008
B83: =B82+0.002 -> 0.05 | C83: 0.39161321 | D83: 0.36581825 | E83: 0.34067373 | F83: 0.31611881 | G83: 0.29209601 | H83: 0.26855076 | I83: 0.24543112 | J83: 0.2226875 | K83: 0.2002724 | L83: 0.17814025 | M83: 0.15624736 | N83: 0.13455185 | O83: 0.1130138 | P83: 0.091595449 | Q83: 0.070261596 | R83: 0.048980222 | S83: 0.027723334 | T83: 0.006468121 | U83: -0.014801572 | V83: -0.036093454 | W83: -0.057404735
B84: =B83+0.002 -> 0.052 | C84: 0.39320634 | D84: 0.36740375 | E84: 0.34225359 | F84: 0.31769508 | G84: 0.29367075 | H84: 0.27012607 | I84: 0.24700916 | J84: 0.22427044 | K84: 0.20186247 | L84: 0.17973973 | M84: 0.15785854 | N84: 0.13617706 | O84: 0.11465535 | P84: 0.09325559 | Q84: 0.071942498 | R84: 0.050683875 | S84: 0.029451453 | T84: 0.0082220118 | U84: -0.013021179 | V84: -0.034286604 | W84: -0.055572478
B85: =B84+0.002 -> 0.054 | C85: 0.39479642 | D85: 0.3689861 | E85: 0.34383022 | F85: 0.31926799 | G85: 0.29524201 | H85: 0.27169777 | I85: 0.24858342 | J85: 0.22584944 | K85: 0.20344843 | L85: 0.1813349 | M85: 0.15946522 | N85: 0.13779755 | O85: 0.11629195 | P85: 0.09491057 | Q85: 0.073618017 | R85: 0.052381931 | S85: 0.031173782 | T85: 0.0099699548 | U85: -0.011246837 | V85: -0.032485834 | W85: -0.053746229
... B88: =B87+0.002 -> 0.06 | C88: 0.39954856 | D88: 0.37371451 | E88: 0.34854082 | F88: 0.3239668 | G88: 0.29993511 | H88: 0.27639137 | I88: 0.25328383 | J88: 0.23056311 | K88: 0.20818193 | L88: 0.18609493 | M88: 0.16425857 | N88: 0.14263108 | O88: 0.12117251 | P88: 0.099844914 | Q88: 0.078612646 | R88: 0.057442893 | S88: 0.036306392 | T88: 0.015178433 | U88: -0.005959837 | V88: -0.02711979 | W88: -0.048303408
A90: Level Premium Scenario | D90: Earned Interest Rate
A91: Renewal Lapse Rates | B91: ='LEVEL PREMIUM Model'!B56 -> 0.1699142 | C91: 0.03 | D91: =C91+0.2% -> 0.032 | E91: =D91+0.2% -> 0.034 | F91: =E91+0.2% -> 0.036 | G91: =F91+0.2% -> 0.038 | H91: =G91+0.2% -> 0.04 | I91: =H91+0.2% -> 0.042 | J91: =I91+0.2% -> 0.044 | K91: =J91+0.2% -> 0.046 | ... R91: =Q91+0.2% -> 0.06
B92: 0.05 | C92: 0.084882451 | D92: 0.090157889 | E92: 0.095419968 | F92: 0.10066832 | G92: 0.10590261 | H92: 0.11112253 | I92: 0.11632782 | J92: 0.12151823 | K92: 0.12669356 | L92: 0.13185362 | M92: 0.13699826 | N92: 0.14212734 | O92: 0.14724074 | P92: 0.15233839 | Q92: 0.15742022 | R92: 0.16248616
B93: =B92+0.01 -> 0.06 | C93: 0.096170442 | D93: 0.1013773 | E93: 0.1065695 | F93: 0.1117468 | G93: 0.11690898 | H93: 0.12205585 | I93: 0.12718725 | J93: 0.13230305 | K93: 0.13740314 | L93: 0.14248743 | M93: 0.14755584 | N93: 0.15260833 | O93: 0.15764487 | P93: 0.16266544 | Q93: 0.16767003 | R93: 0.17265867
B94: =B93+0.01 -> 0.07 | C94: 0.10718691 | D94: 0.11231974 | E94: 0.11743706 | F94: 0.12253876 | G94: 0.1276247 | H94: 0.13269481 | I94: 0.137749 | J94: 0.14278724 | K94: 0.14780948 | L94: 0.15281572 | M94: 0.15780596 | N94: 0.1627802 | O94: 0.16773849 | P94: 0.17268087 | Q94: 0.17760738 | R94: 0.18251809
B95: =B94+0.01 -> 0.08 | C95: 0.11790616 | D95: 0.12296125 | E95: 0.12800039 | F95: 0.13302356 | G95: 0.1380307 | H95: 0.14302182 | I95: 0.1479969 | J95: 0.15295597 | K95: 0.15789906 | L95: 0.16282621 | M95: 0.16773748 | N95: 0.17263294 | O95: 0.17751266 | P95: 0.18237672 | Q95: 0.18722523 | R95: 0.19205829
B96: =B95+0.01 -> 0.09 | C96: 0.12830915 | D96: 0.13328432 | E96: 0.13824345 | F96: 0.14318654 | G96: 0.14811365 | H96: 0.1530248 | I96: 0.15792006 | J96: 0.1627995 | K96: 0.1676632 | L96: 0.17251124 | M96: 0.17734372 | N96: 0.18216074 | O96: 0.18696242 | P96: 0.19174887 | Q96: 0.19652022 | R96: 0.2012766
B97: =B96+0.01 -> 0.1 | C97: 0.13838277 | D97: 0.14327713 | E97: 0.1481556 | F97: 0.15301826 | G97: 0.15786517 | H97: 0.16269643 | I97: 0.16751214 | J97: 0.1723124 | K97: 0.17709733 | L97: 0.18186705 | M97: 0.18662168 | N97: 0.19136135 | O97: 0.19608619 | P97: 0.20079636 | Q97: 0.20549198 | R97: 0.2101732
B98: =B97+0.01 -> 0.11 | C98: 0.14811899 | D98: 0.15293271 | E98: 0.1577309 | F98: 0.16251366 | G98: 0.16728111 | H98: 0.17203337 | I98: 0.17677057 | J98: 0.18149283 | K98: 0.18620031 | L98: 0.19089313 | M98: 0.19557143 | N98: 0.20023538 | O98: 0.20488512 | P98: 0.20952079 | Q98: 0.21414257 | R98: 0.21875059
B99: =B98+0.01 -> 0.12 | C99: 0.15751408 | D99: 0.16224815 | E99: 0.1669672 | F99: 0.17167135 | G99: 0.17636075 | H99: 0.18103554 | I99: 0.18569586 | J99: 0.19034187 | K99: 0.19497371 | L99: 0.19959153 | M99: 0.2041955 | N99: 0.20878577 | O99: 0.2133625 | P99: 0.21792584 | Q99: 0.22247597 | R99: 0.22701303
B100: =B99+0.01 -> 0.13 | C100: 0.16656779 | D100: 0.17122385 | E100: 0.1758655 | F100: 0.18049289 | G100: 0.18510617 | H100: 0.18970549 | I100: 0.19429101 | J100: 0.1988629 | K100: 0.2034213 | L100: 0.20796639 | M100: 0.21249831 | N100: 0.21701724 | O100: 0.22152334 | P100: 0.22601675 | Q100: 0.23049766 | R100: 0.23496622
B101: =B100+0.01 -> 0.14 | C101: 0.17528268 | D101: 0.17986284 | E101: 0.18442927 | F101: 0.18898213 | G101: 0.19352159 | H101: 0.19804779 | I101: 0.20256091 | J101: 0.20706111 | K101: 0.21154854 | L101: 0.21602338 | M101: 0.22048578 | N101: 0.2249359 | O101: 0.22937391 | P101: 0.23379997 | Q101: 0.23821423 | R101: 0.24261685
B102: =B101+0.01 -> 0.15 | C102: 0.18366348 | D102: 0.18817018 | E102: 0.19266388 | F102: 0.19714474 | G102: 0.20161293 | H102: 0.2060686 | I102: 0.21051192 | J102: 0.21494304 | K102: 0.21936214 | L102: 0.22376938 | M102: 0.2281649 | N102: 0.23254887 | O102: 0.23692146 | P102: 0.2412828 | Q102: 0.24563306 | R102: 0.2499724
B103: =B102+0.01 -> 0.16 | C103: 0.19171655 | D103: 0.19615247 | E103: 0.20057613 | F103: 0.2049877 | G103: 0.20938733 | H103: 0.21377519 | I103: 0.21815144 | J103: 0.22251623 | K103: 0.22686973 | L103: 0.23121209 | M103: 0.23554346 | N103: 0.23986399 | O103: 0.24417385 | P103: 0.24847318 | Q103: 0.25276212 | R103: 0.25704083
B104: =B103+0.01 -> 0.17 | C104: 0.19944951 | D104: 0.20381745 | E104: 0.20817387 | F104: 0.21251895 | G104: 0.21685284 | H104: 0.22117569 | I104: 0.22548766 | J104: 0.2297889 | K104: 0.23407956 | L104: 0.2383598 | M104: 0.24262976 | N104: 0.24688958 | O104: 0.25113942 | P104: 0.25537941 | Q104: 0.25960971 | R104: 0.26383044
B105: =B104+0.01 -> 0.18 | C105: 0.20687078 | D105: 0.21117361 | E105: 0.21546567 | F105: 0.21974712 | G105: 0.22401809 | H105: 0.22827875 | I105: 0.23252925 | J105: 0.23676972 | K105: 0.24100031 | L105: 0.24522117 | M105: 0.24943244 | N105: 0.25363425 | O105: 0.25782674 | P105: 0.26201005 | Q105: 0.26618432 | R105: 0.27034967
A107: YRT Scenario | D107: Earned Interest Rate
A108: Renewal Lapse Rates | B108: ='YRT Model'!B56 -> 0.15057227 | C108: 0.03 | D108: =C108+0.2% -> 0.032 | E108: =D108+0.2% -> 0.034 | F108: =E108+0.2% -> 0.036 | G108: =F108+0.2% -> 0.038 | H108: =G108+0.2% -> 0.04 | I108: =H108+0.2% -> 0.042 | J108: =I108+0.2% -> 0.044 | K108: =J108+0.2% -> 0.046 | ... R108: =Q108+0.2% -> 0.06
B109: 0.05 | C109: 0.17674112 | D109: 0.17848915 | E109: 0.18023164 | F109: 0.18196863 | G109: 0.18370016 | H109: 0.18542629 | I109: 0.18714704 | J109: 0.18886246 | K109: 0.1905726 | L109: 0.19227749 | M109: 0.19397718 | N109: 0.1956717 | O109: 0.1973611 | P109: 0.19904541 | Q109: 0.20072467 | R109: 0.20239892
B110: =B109+0.01 -> 0.06 | C110: 0.1693896 | D110: 0.17111935 | E110: 0.17284371 | F110: 0.17456272 | G110: 0.17627641 | H110: 0.17798483 | I110: 0.17968801 | J110: 0.181386 | K110: 0.18307884 | L110: 0.18476657 | M110: 0.18644922 | N110: 0.18812684 | O110: 0.18979945 | P110: 0.19146711 | Q110: 0.19312985 | R110: 0.1947877
B111: =B110+0.01 -> 0.07 | C111: 0.16202764 | D111: 0.16373926 | E111: 0.16544564 | F111: 0.16714679 | G111: 0.16884277 | H111: 0.17053361 | I111: 0.17221936 | J111: 0.17390004 | K111: 0.17557571 | L111: 0.17724639 | M111: 0.17891212 | N111: 0.18057295 | O111: 0.18222891 | P111: 0.18388003 | Q111: 0.18552636 | R111: 0.18716792
B112: =B111+0.01 -> 0.08 | C112: 0.15465537 | D112: 0.156349 | E112: 0.15803752 | F112: 0.15972096 | G112: 0.16139936 | H112: 0.16307276 | I112: 0.1647412 | J112: 0.1664047 | K112: 0.16806332 | L112: 0.16971708 | M112: 0.17136602 | N112: 0.17301018 | O112: 0.1746496 | P112: 0.1762843 | Q112: 0.17791433 | R112: 0.17953971
B113: =B112+0.01 -> 0.09 | C113: 0.14727292 | D113: 0.14894871 | E113: 0.15061951 | F113: 0.15228538 | G113: 0.15394633 | H113: 0.15560242 | I113: 0.15725367 | J113: 0.15890012 | K113: 0.16054181 | L113: 0.16217878 | M113: 0.16381105 | N113: 0.16543866 | O113: 0.16706165 | P113: 0.16868005 | Q113: 0.17029389 | R113: 0.17190321
B114: =B113+0.01 -> 0.1 | C114: 0.13988044 | D114: 0.14153852 | E114: 0.14319175 | F114: 0.14484017 | G114: 0.14648381 | H114: 0.14812272 | I114: 0.14975692 | J114: 0.15138645 | K114: 0.15301134 | L114: 0.15463163 | M114: 0.15624736 | N114: 0.15785854 | O114: 0.15946522 | P114: 0.16106744 | Q114: 0.16266521 | R114: 0.16425857
B115: =B114+0.01 -> 0.11 | C115: 0.13247808 | D115: 0.13411858 | E115: 0.13575438 | F115: 0.13738549 | G115: 0.13901196 | H115: 0.14063382 | I115: 0.1422511 | J115: 0.14386384 | K115: 0.14547206 | L115: 0.1470758 | M115: 0.1486751 | N115: 0.15026998 | O115: 0.15186047 | P115: 0.15344661 | Q115: 0.15502843 | R115: 0.15660596
B116: =B115+0.01 -> 0.12 | C116: 0.12506599 | D116: 0.12668908 | E116: 0.12830757 | F116: 0.12992152 | G116: 0.13153095 | H116: 0.13313589 | I116: 0.13473638 | J116: 0.13633245 | K116: 0.13792413 | L116: 0.13951145 | M116: 0.14109444 | N116: 0.14267313 | O116: 0.14424756 | P116: 0.14581775 | Q116: 0.14738373 | R116: 0.14894553
B117: =B116+0.01 -> 0.13 | C117: 0.11764437 | D117: 0.11925017 | E117: 0.12085151 | F117: 0.12244842 | G117: 0.12404095 | H117: 0.12562911 | I117: 0.12721294 | J117: 0.12879247 | K117: 0.13036774 | L117: 0.13193876 | M117: 0.13350557 | N117: 0.1350682 | O117: 0.13662668 | P117: 0.13818103 | Q117: 0.13973129 | R117: 0.14127748
B118: =B117+0.01 -> 0.14 | C118: 0.11021339 | D118: 0.11180204 | E118: 0.11338637 | F118: 0.11496639 | G118: 0.11654215 | H118: 0.11811366 | I118: 0.11968097 | J118: 0.12124409 | K118: 0.12280307 | L118: 0.12435792 | M118: 0.12590867 | N118: 0.12745536 | O118: 0.12899801 | P118: 0.13053665 | Q118: 0.13207131 | R118: 0.13360201
B119: =B118+0.01 -> 0.15 | C119: 0.10277326 | D119: 0.10434491 | E119: 0.10591236 | F119: 0.10747563 | G119: 0.10903475 | H119: 0.11058976 | I119: 0.11214067 | J119: 0.11368752 | K119: 0.11523033 | L119: 0.11676914 | M119: 0.11830396 | N119: 0.11983483 | O119: 0.12136178 | P119: 0.12288482 | Q119: 0.12440399 | R119: 0.12591931
B120: =B119+0.01 -> 0.16 | C120: 0.095324188 | D120: 0.096878985 | E120: 0.098429697 | F120: 0.099976353 | G120: 0.10151898 | H120: 0.10305761 | I120: 0.10459226 | J120: 0.10612296 | K120: 0.10764975 | L120: 0.10917264 | M120: 0.11069166 | N120: 0.11220683 | O120: 0.11371819 | P120: 0.11522576 | Q120: 0.11672956 | R120: 0.11822962
B121: =B120+0.01 -> 0.17 | C121: 0.087866409 | D121: 0.089404493 | E121: 0.090938612 | F121: 0.092468793 | G121: 0.093995063 | H121: 0.095517447 | I121: 0.097035972 | J121: 0.098550663 | K121: 0.10006155 | L121: 0.10156864 | M121: 0.10307199 | N121: 0.10457159 | O121: 0.10606749 | P121: 0.1075597 | Q121: 0.10904825 | R121: 0.11053317
B122: =B121+0.01 -> 0.18 | C122: 0.080400167 | D122: 0.081921682 | E122: 0.08343935 | F122: 0.084953196 | G122: 0.086463246 | H122: 0.087969525 | I122: 0.089472057 | J122: 0.090970867 | K122: 0.092465978 | L122: 0.093957416 | M122: 0.095445204 | N122: 0.096929366 | O122: 0.098409924 | P122: 0.099886903 | Q122: 0.10136032 | R122: 0.10283021
